Workbook
Name MileageRate: 'Settings'!$B$4
Name MarketRankingMinimumVisits: 'Settings'!$B$5
Name TestingMode: 'Settings'!$B$7
Name WeeklyProfitGoal: 'Settings'!$B$8
Name CurrentWeekStart: =TODAY()-WEEKDAY(TODAY(),2)+1
Name CurrentWeekEnd: =CurrentWeekStart+6
Name CurrentMonthStart: =EOMONTH(TODAY(),-1)+1
Name CurrentYearStart: =DATE(YEAR(TODAY()),1,1)
Name MissingImportCount: 'Operations_Dashboard'!$B$5
Name ProductsRequiringAction: 'Operations_Dashboard'!$E$5
Name InventoryIssueCount: 'Operations_Dashboard'!$H$5
Name MarketMasterIssueCount: 'Operations_Dashboard'!$K$4
Name fxWorkbookHealth: 'Operations_Dashboard'!$B$4
Name fxWeeklyRevenue: 'Business_Dashboard'!$B$4
Name fxWeeklyProfit: 'Business_Dashboard'!$B$10
Name WorkbookVersion: 'Workbook_Version'!$A$4

Sheet Testing_Dashboard
A1: Enterprise Testing Dashboard
A3: Total Tests | B3: =ROWS(tblRegressionTests[Test ID]) | D3: Category | E3: Total | F3: Passed | G3: Failed
A4: Passed | B4: =COUNTIF(tblRegressionTests[Status],"PASS") | D4: Dashboard | E4: =COUNTIF(tblRegressionTests[Category],D4) | F4: =COUNTIFS(tblRegressionTests[Category],D4,tblRegressionTests[Status],"PASS") | G4: =COUNTIFS(tblRegressionTests[Category],D4,tblRegressionTests[Status],"FAIL")
A5: Failed | B5: =COUNTIF(tblRegressionTests[Status],"FAIL") | D5: Inventory | E5: =COUNTIF(tblRegressionTests[Category],D5) | F5: =COUNTIFS(tblRegressionTests[Category],D5,tblRegressionTests[Status],"PASS") | G5: =COUNTIFS(tblRegressionTests[Category],D5,tblRegressionTests[Status],"FAIL")
A6: Pass Rate | B6: =IFERROR(B4/B3,0) | D6: Product | E6: =COUNTIF(tblRegressionTests[Category],D6) | F6: =COUNTIFS(tblRegressionTests[Category],D6,tblRegressionTests[Status],"PASS") | G6: =COUNTIFS(tblRegressionTests[Category],D6,tblRegressionTests[Status],"FAIL")
A7: Release Gate | B7: =IF(B5=0,"READY","BLOCKED") | D7: Market | E7: =COUNTIF(tblRegressionTests[Category],D7) | F7: =COUNTIFS(tblRegressionTests[Category],D7,tblRegressionTests[Status],"PASS") | G7: =COUNTIFS(tblRegressionTests[Category],D7,tblRegressionTests[Status],"FAIL")
D8: Governance | E8: =COUNTIF(tblRegressionTests[Category],D8) | F8: =COUNTIFS(tblRegressionTests[Category],D8,tblRegressionTests[Status],"PASS") | G8: =COUNTIFS(tblRegressionTests[Category],D8,tblRegressionTests[Status],"FAIL")

Sheet START_HERE
A1: START HERE
A3: Golden Rule
A4: Weekly use should require only: (1) place Square export files, (2) Refresh All, (3) complete Weekly Entry, and review dashboards.
A6: Step | B6: Action
A7: 1 | B7: Place Square export file(s) in the approved folder.
A8: 2 | B8: Data > Refresh All.
A9: 3 | B9: Complete Weekly_Entry: markets, production exceptions, purchases, expenses.
A10: 4 | B10: Review Operations_Dashboard, then Business_Dashboard.
A11: 5 | B11: Run TESTING before increasing the workbook version.
A14: Product ID warning
A15: Use Square Variation ID as the product key. Confirm the Square export contains Variation ID. If not, import a catalog export and map by SKU or Item + Variation name. Do not permanently match by product name alone.
A18: Refresh sequence
A19: Order | B19: Refresh Step
A20: 1 | B20: Import Square files
A21: 2 | B21: Refresh staging queries
A22: 3 | B22: Refresh Product Master
A23: 4 | B23: Refresh Inventory and rankings
A24: 5 | B24: Refresh dashboards
A25: 6 | B25: Run TESTING
A28: Market Master governance
A29: Never edit a historical market-default row. End-date it and add a new row. Market Master defines cost/mileage defaults only and does not imply attendance.
A32: v3.0 Additions
A33: Executive dashboard, Monthly/YTD KPIs, reorder engine, inventory valuation, forecasting, product scorecards, market opportunity scoring, data quality dashboard, release certification, and Power Query stubs.
A36: Regression Testing
A37: Use Regression_Summary for the release gate and Regression_Tests for detailed diagnostics. The suite contains 110 automated tests across dashboards, inventory, products, markets, and governance.

Sheet Weekly_Entry
A1: WEEKLY ENTRY
A3: Markets
A4: Test Key | B4: Market Date | C4: Market | D4: Market Status | E4: Market Day Score | F4: Notes | G4: Override Miles | H4: Attendance Category | I4: Market Match Count | J4: Market Fee | K4: Actual Miles | L4: Travel Cost | M4: Imported Sales Rows | N4: Import Status | O4: Test Record
A5: TEST-MKT-01 | B5: 46027 | C5: TEST-ORLANDO | D5: Attended | E5: Good | F5: Fixture | H5: =IF(OR(tblWeeklyMarkets[[#This Row],[Market Status]]="Attended",tblWeeklyMarkets[[#This Row],[Market Status]]="Partial Day"),"Attended",IF(OR(tblWeeklyMarkets[[#This Row],[Market Status]]="Vacation",tblWeeklyMarkets[[#This Row],[Market Status]]="Family",tblWeeklyMarkets[[#This Row],[Market Status]]="Personal",tblWeeklyMarkets[[#This Row],[Market Status]]="Illness",tblWeeklyMarkets[[#This Row],[Market Status]]="Emergency"),"Excluded","Not Attended")) | I5: =SUMPRODUCT(--(tblMarketMaster[Market]=tblWeeklyMarkets[[#This Row],[Market]]),--(tblMarketMaster[Start Date]<=tblWeeklyMarkets[[#This Row],[Market Date]]),--(IF(tblMarketMaster[End Date]="",DATE(9999,12,31),tblMarketMaster[End Date])>=tblWeeklyMarkets[[#This Row],[Market Date]])) | J5: =IF(tblWeeklyMarkets[[#This Row],[Attendance Category]]<>"Attended",0,IF(tblWeeklyMarkets[[#This Row],[Market Match Count]]<>1,"",_xlfn.XLOOKUP(1,(tblMarketMaster[Market]=tblWeeklyMarkets[[#This Row],[Market]])*(tblMarketMaster[Start Date]<=tblWeeklyMarkets[[#This Row],[Market Date]])*(IF(tblMarketMaster[End Date]="",DATE(9999,12,31),tblMarketMaster[End Date])>=tblWeeklyMarkets[[#This Row],[Market Date]]),tblMarketMaster[Market Fee],""))) | K5: =IF(tblWeeklyMarkets[[#This Row],[Attendance Category]]<>"Attended",0,IF(tblWeeklyMarkets[[#This Row],[Override Miles]]<>"",tblWeeklyMarkets[[#This Row],[Override Miles]],IF(tblWeeklyMarkets[[#This Row],[Market Match Count]]<>1,"",_xlfn.XLOOKUP(1,(tblMarketMaster[Market]=tblWeeklyMarkets[[#This Row],[Market]])*(tblMarketMaster[Start Date]<=tblWeeklyMarkets[[#This Row],[Market Date]])*(IF(tblMarketMaster[End Date]="",DATE(9999,12,31),tblMarketMaster[End Date])>=tblWeeklyMarkets[[#This Row],[Market Date]]),tblMarketMaster[Default Round Trip Miles],"")))) | L5: =IFERROR(tblWeeklyMarkets[[#This Row],[Actual Miles]]*MileageRate,0) | M5: =COUNTIFS(tblSalesData[Sale Timestamp],">="&tblWeeklyMarkets[[#This Row],[Market Date]],tblSalesData[Sale Timestamp],"<"&(tblWeeklyMarkets[[#This Row],[Market Date]]+1),tblSalesData[Test Record],tblWeeklyMarkets[[#This Row],[Test Record]]) | N5: =IF(tblWeeklyMarkets[[#This Row],[Attendance Category]]="Excluded","EXCLUDED",IF(tblWeeklyMarkets[[#This Row],[Attendance Category]]<>"Attended","NOT EXPECTED",IF(tblWeeklyMarkets[[#This Row],[Imported Sales Rows]]>0,"IMPORTED","SALES DATA NOT IMPORTED"))) | O5: Yes
A6: TEST-MKT-02 | B6: 46034 | C6: TEST-ORLANDO | D6: Vacation | E6: Average | F6: Fixture | H6: =IF(OR(tblWeeklyMarkets[[#This Row],[Market Status]]="Attended",tblWeeklyMarkets[[#This Row],[Market Status]]="Partial Day"),"Attended",IF(OR(tblWeeklyMarkets[[#This Row],[Market Status]]="Vacation",tblWeeklyMarkets[[#This Row],[Market Status]]="Family",tblWeeklyMarkets[[#This Row],[Market Status]]="Personal",tblWeeklyMarkets[[#This Row],[Market Status]]="Illness",tblWeeklyMarkets[[#This Row],[Market Status]]="Emergency"),"Excluded","Not Attended")) | I6: =SUMPRODUCT(--(tblMarketMaster[Market]=tblWeeklyMarkets[[#This Row],[Market]]),--(tblMarketMaster[Start Date]<=tblWeeklyMarkets[[#This Row],[Market Date]]),--(IF(tblMarketMaster[End Date]="",DATE(9999,12,31),tblMarketMaster[End Date])>=tblWeeklyMarkets[[#This Row],[Market Date]])) | J6: =IF(tblWeeklyMarkets[[#This Row],[Attendance Category]]<>"Attended",0,IF(tblWeeklyMarkets[[#This Row],[Market Match Count]]<>1,"",_xlfn.XLOOKUP(1,(tblMarketMaster[Market]=tblWeeklyMarkets[[#This Row],[Market]])*(tblMarketMaster[Start Date]<=tblWeeklyMarkets[[#This Row],[Market Date]])*(IF(tblMarketMaster[End Date]="",DATE(9999,12,31),tblMarketMaster[End Date])>=tblWeeklyMarkets[[#This Row],[Market Date]]),tblMarketMaster[Market Fee],""))) | K6: =IF(tblWeeklyMarkets[[#This Row],[Attendance Category]]<>"Attended",0,IF(tblWeeklyMarkets[[#This Row],[Override Miles]]<>"",tblWeeklyMarkets[[#This Row],[Override Miles]],IF(tblWeeklyMarkets[[#This Row],[Market Match Count]]<>1,"",_xlfn.XLOOKUP(1,(tblMarketMaster[Market]=tblWeeklyMarkets[[#This Row],[Market]])*(tblMarketMaster[Start Date]<=tblWeeklyMarkets[[#This Row],[Market Date]])*(IF(tblMarketMaster[End Date]="",DATE(9999,12,31),tblMarketMaster[End Date])>=tblWeeklyMarkets[[#This Row],[Market Date]]),tblMarketMaster[Default Round Trip Miles],"")))) | L6: =IFERROR(tblWeeklyMarkets[[#This Row],[Actual Miles]]*MileageRate,0) | M6: =COUNTIFS(tblSalesData[Sale Timestamp],">="&tblWeeklyMarkets[[#This Row],[Market Date]],tblSalesData[Sale Timestamp],"<"&(tblWeeklyMarkets[[#This Row],[Market Date]]+1),tblSalesData[Test Record],tblWeeklyMarkets[[#This Row],[Test Record]]) | N6: =IF(tblWeeklyMarkets[[#This Row],[Attendance Category]]="Excluded","EXCLUDED",IF(tblWeeklyMarkets[[#This Row],[Attendance Category]]<>"Attended","NOT EXPECTED",IF(tblWeeklyMarkets[[#This Row],[Imported Sales Rows]]>0,"IMPORTED","SALES DATA NOT IMPORTED"))) | O6: Yes
A10: Production Exceptions
A11: Week Start | B11: Variation ID | C11: Product Name | D11: Quantity Made | E11: Samples Given | F11: Notes | G11: Test Record
A12: 46027 | B12: TEST-VAR001 | C12: Test Jam 8 oz | D12: 20 | E12: 2 | F12: Fixture | G12: Yes
A16: Purchase Date | B16: Purchase Type | C16: Store | D16: Receipt ID | E16: Ingredient | F16: Quantity | G16: Unit | H16: Total Cost | I16: Notes | J16: Validation | K16: Test Record
A17: 46027 | B17: Item | C17: Test Store | D17: R-TEST-1 | E17: Sugar | F17: 25 | G17: lb | H17: 18 | I17: Fixture | J17: =IF(AND(tblIngredientPurchases[[#This Row],[Purchase Type]]="Item",OR(tblIngredientPurchases[[#This Row],[Ingredient]]="",tblIngredientPurchases[[#This Row],[Quantity]]="")),"INCOMPLETE","OK") | K17: Yes
A21: Date | B21: Category | C21: Amount | D21: Description | E21: Test Record
A22: 46027 | B22: Packaging | C22: 12 | D22: Fixture | E22: Yes

Sheet Product_Setup
A1: PRODUCT SETUP
A3: Variation ID | B3: Item ID | C3: Product Name | D3: Variation Name | E3: Shelf Stable | F3: Spoils If Unsold | G3: Product Group | H3: Product Active | I3: Recipe Complete | J3: Cost Complete | K3: Product Status | L3: Missing Items | M3: Effective Product Cost | N3: Test Record
A4: TEST-VAR001 | B4: TEST-ITEM1 | C4: Test Strawberry Jam | D4: 8 oz | E4: Yes | F4: Yes | G4: Jam | H4: Yes | I4: Yes | J4: Yes | K4: READY | M4: 2.15 | N4: Yes
A5: TEST-VAR002 | B5: TEST-ITEM1 | C5: Test Strawberry Jam | D5: 16 oz | E5: Yes | F5: No | G5: Jam | H5: Yes | I5: Yes | J5: No | K5: SETUP REQUIRED | L5: Cost | N5: Yes
A6: TEST-VAR003 | B6: TEST-ITEM2 | C6: Test Fresh Bread | D6: Regular | E6: No | F6: Yes | G6: Fresh | H6: Yes | I6: No | J6: Yes | K6: SETUP REQUIRED | L6: Recipe | M6: 1.5 | N6: Yes
A7: TEST-VAR004 | B7: TEST-ITEM3 | C7: Test Hot Honey | D7: Regular | E7: Yes | F7: Yes | G7: Honey | H7: Yes | I7: No | J7: No | K7: CONFIGURE PRODUCT | L7: Recipe, Cost | N7: Yes

Sheet Operations_Dashboard
A1: OPERATIONS DASHBOARD
A3: Import Health | D3: Product Health | G3: Inventory Health | J3: Market Master Health
A4: Workbook Health | B4: =_xlfn.IFS(B5>0,"SALES DATA NOT IMPORTED",E6>0,"PRODUCT SETUP REQUIRED",K5>0,"MARKET MASTER REVIEW REQUIRED",H6>0,"INVENTORY REVIEW REQUIRED",TRUE,"WORKBOOK HEALTHY") | D4: Products Ready | E4: =COUNTIFS(tblProductMaster[Product Status],"READY",tblProductMaster[Test Record],"No") | G4: Snapshot Date | H4: =IFERROR(_xlfn.MAXIFS(tblInventory[Inventory Date],tblInventory[Test Record],"No"),"") | J4: Configuration Issues | K4: =COUNTIFS(tblMarketMaster[Overlap Count],">0",tblMarketMaster[Test Record],"No")+COUNTIFS(tblMarketMaster[Fee Validation],"<>OK",tblMarketMaster[Test Record],"No")+COUNTIFS(tblMarketMaster[Invalid Date Range],"INVALID",tblMarketMaster[Test Record],"No")
A5: Missing Imports | B5: =COUNTIFS(tblWeeklyMarkets[Import Status],"SALES DATA NOT IMPORTED",tblWeeklyMarkets[Test Record],"No") | D5: Products Requiring Action | E5: =COUNTIFS(tblProductMaster[Product Status],"<>READY",tblProductMaster[Test Record],"No") | G5: Inventory Movement Errors | H5: =COUNTIFS(tblInventory[Validation],"<>OK",tblInventory[Test Record],"No")
A6: Imported Markets | B6: =COUNTIFS(tblWeeklyMarkets[Import Status],"IMPORTED",tblWeeklyMarkets[Test Record],"No") | D6: Missing Recipes | E6: =COUNTIFS(tblProductMaster[Recipe Complete],"No",tblProductMaster[Test Record],"No") | G6: Current Inventory Units | H6: =_xlfn.LET(Dt,IFERROR(_xlfn.MAXIFS(tblInventory[Inventory Date],tblInventory[Test Record],"No"),0),IF(Dt=0,0,SUMIFS(tblInventory[Ending Inventory],tblInventory[Inventory Date],Dt,tblInventory[Test Record],"No")))
A7: Excluded Markets | B7: =COUNTIFS(tblWeeklyMarkets[Import Status],"EXCLUDED",tblWeeklyMarkets[Test Record],"No") | D7: Missing Costs | E7: =COUNTIFS(tblProductMaster[Cost Complete],"No",tblProductMaster[Test Record],"No")
A8: Last Successful Import | B8: =IFERROR(_xlfn.MAXIFS(tblImportLog[Import Timestamp],tblImportLog[Status],"Success",tblImportLog[Test Record],"No"),"")

Sheet Business_Dashboard
A1: BUSINESS DASHBOARD
A3: Weekly Performance | D3: Rankings | G3: Setup / Waste
A4: Weekly Revenue | B4: =SUMIFS(tblSalesData[Gross Sales],tblSalesData[Sale Timestamp],">="&CurrentWeekStart,tblSalesData[Sale Timestamp],"<"&CurrentWeekEnd+1,tblSalesData[Test Record],"No") | D4: Best Product | E4: =IFERROR(_xlfn.XLOOKUP(1,(tblProductRankings[Profit Rank]=1)*(tblProductRankings[Test Record]="No"),tblProductRankings[Product Name]),"No ranked products") | G4: Product Setup Completion | H4: =IFERROR(COUNTIFS(tblProductMaster[Product Status],"READY",tblProductMaster[Test Record],"No")/COUNTIFS(tblProductMaster[Test Record],"No"),0)
A5: Weekly COGS | B5: =SUMIFS(tblSalesData[COGS],tblSalesData[Sale Timestamp],">="&CurrentWeekStart,tblSalesData[Sale Timestamp],"<"&CurrentWeekEnd+1,tblSalesData[Test Record],"No") | D5: Best Business Market | E5: =IFERROR(_xlfn.XLOOKUP(1,(tblMarketRankings[Business Rank]=1)*(tblMarketRankings[Test Record]="No"),tblMarketRankings[Market]),"No ranked markets") | G5: Waste % | H5: =IFERROR(SUMIFS(tblInventory[Spoilage],tblInventory[Test Record],"No")/SUMIFS(tblInventory[Available],tblInventory[Test Record],"No"),0)
A6: Weekly Market Fees | B6: =SUMIFS(tblWeeklyMarkets[Market Fee],tblWeeklyMarkets[Market Date],">="&CurrentWeekStart,tblWeeklyMarkets[Market Date],"<="&CurrentWeekEnd,tblWeeklyMarkets[Attendance Category],"Attended",tblWeeklyMarkets[Test Record],"No") | D6: Best Travel-Adjusted Market | E6: =IFERROR(_xlfn.XLOOKUP(1,(tblMarketRankings[Personal Rank]=1)*(tblMarketRankings[Test Record]="No"),tblMarketRankings[Market]),"No ranked markets") | G6: Inventory As Of | H6: =IFERROR(_xlfn.MAXIFS(tblInventory[Inventory Date],tblInventory[Test Record],"No"),"")
A7: Weekly Travel Cost | B7: =SUMIFS(tblWeeklyMarkets[Travel Cost],tblWeeklyMarkets[Market Date],">="&CurrentWeekStart,tblWeeklyMarkets[Market Date],"<="&CurrentWeekEnd,tblWeeklyMarkets[Attendance Category],"Attended",tblWeeklyMarkets[Test Record],"No") | D7: Ranked Markets | E7: =COUNTIFS(tblMarketRankings[Eligibility],"Eligible",tblMarketRankings[Test Record],"No")
A8: Weekly Square Fees | B8: =SUMIFS(tblSalesData[Square Fee],tblSalesData[Sale Timestamp],">="&CurrentWeekStart,tblSalesData[Sale Timestamp],"<"&CurrentWeekEnd+1,tblSalesData[Test Record],"No") | D8: Not Ranked Markets | E8: =COUNTIFS(tblMarketRankings[Eligibility],"Not Ranked",tblMarketRankings[Test Record],"No")
A9: Weekly Other Expenses | B9: =SUMIFS(tblExpenses[Amount],tblExpenses[Date],">="&CurrentWeekStart,tblExpenses[Date],"<="&CurrentWeekEnd,tblExpenses[Test Record],"No")
A10: Weekly Profit | B10: =B4-B5-B6-B7-B8-B9

Sheet TESTING
A1: TESTING
A3: Test ID | B3: Test Area | C3: Test Key | D3: Test Date | E3: Expected Result | F3: Actual Result | G3: Status | H3: Notes | J3: Release Status | K3: =IF(COUNTIF(tblTesting[Status],"FAIL")=0,"READY FOR PRODUCTION","TEST FAILURES EXIST")
A4: T020 | B4: Mileage | C4: TEST-MKT-01 | E4: 84 | F4: =_xlfn.SWITCH(tblTesting[[#This Row],[Test ID]],"T020",_xlfn.XLOOKUP(tblTesting[[#This Row],[Test Key]],tblWeeklyMarkets[Test Key],tblWeeklyMarkets[Actual Miles],"NOT FOUND"),"T022",_xlfn.XLOOKUP(tblTesting[[#This Row],[Test Key]],tblWeeklyMarkets[Test Key],tblWeeklyMarkets[Travel Cost],"NOT FOUND"),"T030",_xlfn.XLOOKUP(tblTesting[[#This Row],[Test Key]],tblWeeklyMarkets[Test Key],tblWeeklyMarkets[Attendance Category],"NOT FOUND"),"T032",_xlfn.XLOOKUP(tblTesting[[#This Row],[Test Key]],tblWeeklyMarkets[Test Key],tblWeeklyMarkets[Attendance Category],"NOT FOUND"),"T050",_xlfn.XLOOKUP(tblTesting[[#This Row],[Test Key]],tblInventory[Test Key],tblInventory[Spoilage],"NOT FOUND"),"T052",_xlfn.XLOOKUP(tblTesting[[#This Row],[Test Key]],tblInventory[Test Key],tblInventory[Ending Inventory],"NOT FOUND"),"T060",_xlfn.XLOOKUP(tblTesting[[#This Row],[Test Key]],tblIngredientUsage[Test Key],tblIngredientUsage[Quantity Used],"NOT FOUND"),"T080",_xlfn.XLOOKUP(tblTesting[[#This Row],[Test Key]],tblProductMaster[Variation ID],tblProductMaster[Cost Complete],"NOT FOUND"),"T081",_xlfn.XLOOKUP(tblTesting[[#This Row],[Test Key]],tblProductMaster[Variation ID],tblProductMaster[Cost Complete],"NOT FOUND"),"T082",_xlfn.XLOOKUP(tblTesting[[#This Row],[Test Key]],tblProductCosts[Variation ID],tblProductCosts[Cost Review Status],"NOT FOUND"),"TEST NOT DEFINED") | G4: =IF(OR(tblTesting[[#This Row],[Actual Result]]="NOT FOUND",tblTesting[[#This Row],[Actual Result]]="TEST NOT DEFINED"),"FAIL",IF(AND(ISNUMBER(tblTesting[[#This Row],[Expected Result]]),ISNUMBER(tblTesting[[#This Row],[Actual Result]])),IF(ABS(tblTesting[[#This Row],[Expected Result]]-tblTesting[[#This Row],[Actual Result]])<0.01,"PASS","FAIL"),IF(tblTesting[[#This Row],[Expected Result]]=tblTesting[[#This Row],[Actual Result]],"PASS","FAIL"))) | H4: Default mileage | J4: Passed | K4: =COUNTIF(tblTesting[Status],"PASS")
A5: T022 | B5: Travel Cost | C5: TEST-MKT-01 | E5: 56.28 | F5: =_xlfn.SWITCH(tblTesting[[#This Row],[Test ID]],"T020",_xlfn.XLOOKUP(tblTesting[[#This Row],[Test Key]],tblWeeklyMarkets[Test Key],tblWeeklyMarkets[Actual Miles],"NOT FOUND"),"T022",_xlfn.XLOOKUP(tblTesting[[#This Row],[Test Key]],tblWeeklyMarkets[Test Key],tblWeeklyMarkets[Travel Cost],"NOT FOUND"),"T030",_xlfn.XLOOKUP(tblTesting[[#This Row],[Test Key]],tblWeeklyMarkets[Test Key],tblWeeklyMarkets[Attendance Category],"NOT FOUND"),"T032",_xlfn.XLOOKUP(tblTesting[[#This Row],[Test Key]],tblWeeklyMarkets[Test Key],tblWeeklyMarkets[Attendance Category],"NOT FOUND"),"T050",_xlfn.XLOOKUP(tblTesting[[#This Row],[Test Key]],tblInventory[Test Key],tblInventory[Spoilage],"NOT FOUND"),"T052",_xlfn.XLOOKUP(tblTesting[[#This Row],[Test Key]],tblInventory[Test Key],tblInventory[Ending Inventory],"NOT FOUND"),"T060",_xlfn.XLOOKUP(tblTesting[[#This Row],[Test Key]],tblIngredientUsage[Test Key],tblIngredientUsage[Quantity Used],"NOT FOUND"),"T080",_xlfn.XLOOKUP(tblTesting[[#This Row],[Test Key]],tblProductMaster[Variation ID],tblProductMaster[Cost Complete],"NOT FOUND"),"T081",_xlfn.XLOOKUP(tblTesting[[#This Row],[Test Key]],tblProductMaster[Variation ID],tblProductMaster[Cost Complete],"NOT FOUND"),"T082",_xlfn.XLOOKUP(tblTesting[[#This Row],[Test Key]],tblProductCosts[Variation ID],tblProductCosts[Cost Review Status],"NOT FOUND"),"TEST NOT DEFINED") | G5: =IF(OR(tblTesting[[#This Row],[Actual Result]]="NOT FOUND",tblTesting[[#This Row],[Actual Result]]="TEST NOT DEFINED"),"FAIL",IF(AND(ISNUMBER(tblTesting[[#This Row],[Expected Result]]),ISNUMBER(tblTesting[[#This Row],[Actual Result]])),IF(ABS(tblTesting[[#This Row],[Expected Result]]-tblTesting[[#This Row],[Actual Result]])<0.01,"PASS","FAIL"),IF(tblTesting[[#This Row],[Expected Result]]=tblTesting[[#This Row],[Actual Result]],"PASS","FAIL"))) | H5: 84 miles x 0.67 | J5: Failed | K5: =COUNTIF(tblTesting[Status],"FAIL")
A6: T030 | B6: Attendance | C6: TEST-MKT-01 | E6: Attended | F6: =_xlfn.SWITCH(tblTesting[[#This Row],[Test ID]],"T020",_xlfn.XLOOKUP(tblTesting[[#This Row],[Test Key]],tblWeeklyMarkets[Test Key],tblWeeklyMarkets[Actual Miles],"NOT FOUND"),"T022",_xlfn.XLOOKUP(tblTesting[[#This Row],[Test Key]],tblWeeklyMarkets[Test Key],tblWeeklyMarkets[Travel Cost],"NOT FOUND"),"T030",_xlfn.XLOOKUP(tblTesting[[#This Row],[Test Key]],tblWeeklyMarkets[Test Key],tblWeeklyMarkets[Attendance Category],"NOT FOUND"),"T032",_xlfn.XLOOKUP(tblTesting[[#This Row],[Test Key]],tblWeeklyMarkets[Test Key],tblWeeklyMarkets[Attendance Category],"NOT FOUND"),"T050",_xlfn.XLOOKUP(tblTesting[[#This Row],[Test Key]],tblInventory[Test Key],tblInventory[Spoilage],"NOT FOUND"),"T052",_xlfn.XLOOKUP(tblTesting[[#This Row],[Test Key]],tblInventory[Test Key],tblInventory[Ending Inventory],"NOT FOUND"),"T060",_xlfn.XLOOKUP(tblTesting[[#This Row],[Test Key]],tblIngredientUsage[Test Key],tblIngredientUsage[Quantity Used],"NOT FOUND"),"T080",_xlfn.XLOOKUP(tblTesting[[#This Row],[Test Key]],tblProductMaster[Variation ID],tblProductMaster[Cost Complete],"NOT FOUND"),"T081",_xlfn.XLOOKUP(tblTesting[[#This Row],[Test Key]],tblProductMaster[Variation ID],tblProductMaster[Cost Complete],"NOT FOUND"),"T082",_xlfn.XLOOKUP(tblTesting[[#This Row],[Test Key]],tblProductCosts[Variation ID],tblProductCosts[Cost Review Status],"NOT FOUND"),"TEST NOT DEFINED") | G6: =IF(OR(tblTesting[[#This Row],[Actual Result]]="NOT FOUND",tblTesting[[#This Row],[Actual Result]]="TEST NOT DEFINED"),"FAIL",IF(AND(ISNUMBER(tblTesting[[#This Row],[Expected Result]]),ISNUMBER(tblTesting[[#This Row],[Actual Result]])),IF(ABS(tblTesting[[#This Row],[Expected Result]]-tblTesting[[#This Row],[Actual Result]])<0.01,"PASS","FAIL"),IF(tblTesting[[#This Row],[Expected Result]]=tblTesting[[#This Row],[Actual Result]],"PASS","FAIL"))) | H6: Attended category
A7: T032 | B7: Attendance | C7: TEST-MKT-02 | E7: Excluded | F7: =_xlfn.SWITCH(tblTesting[[#This Row],[Test ID]],"T020",_xlfn.XLOOKUP(tblTesting[[#This Row],[Test Key]],tblWeeklyMarkets[Test Key],tblWeeklyMarkets[Actual Miles],"NOT FOUND"),"T022",_xlfn.XLOOKUP(tblTesting[[#This Row],[Test Key]],tblWeeklyMarkets[Test Key],tblWeeklyMarkets[Travel Cost],"NOT FOUND"),"T030",_xlfn.XLOOKUP(tblTesting[[#This Row],[Test Key]],tblWeeklyMarkets[Test Key],tblWeeklyMarkets[Attendance Category],"NOT FOUND"),"T032",_xlfn.XLOOKUP(tblTesting[[#This Row],[Test Key]],tblWeeklyMarkets[Test Key],tblWeeklyMarkets[Attendance Category],"NOT FOUND"),"T050",_xlfn.XLOOKUP(tblTesting[[#This Row],[Test Key]],tblInventory[Test Key],tblInventory[Spoilage],"NOT FOUND"),"T052",_xlfn.XLOOKUP(tblTesting[[#This Row],[Test Key]],tblInventory[Test Key],tblInventory[Ending Inventory],"NOT FOUND"),"T060",_xlfn.XLOOKUP(tblTesting[[#This Row],[Test Key]],tblIngredientUsage[Test Key],tblIngredientUsage[Quantity Used],"NOT FOUND"),"T080",_xlfn.XLOOKUP(tblTesting[[#This Row],[Test Key]],tblProductMaster[Variation ID],tblProductMaster[Cost Complete],"NOT FOUND"),"T081",_xlfn.XLOOKUP(tblTesting[[#This Row],[Test Key]],tblProductMaster[Variation ID],tblProductMaster[Cost Complete],"NOT FOUND"),"T082",_xlfn.XLOOKUP(tblTesting[[#This Row],[Test Key]],tblProductCosts[Variation ID],tblProductCosts[Cost Review Status],"NOT FOUND"),"TEST NOT DEFINED") | G7: =IF(OR(tblTesting[[#This Row],[Actual Result]]="NOT FOUND",tblTesting[[#This Row],[Actual Result]]="TEST NOT DEFINED"),"FAIL",IF(AND(ISNUMBER(tblTesting[[#This Row],[Expected Result]]),ISNUMBER(tblTesting[[#This Row],[Actual Result]])),IF(ABS(tblTesting[[#This Row],[Expected Result]]-tblTesting[[#This Row],[Actual Result]])<0.01,"PASS","FAIL"),IF(tblTesting[[#This Row],[Expected Result]]=tblTesting[[#This Row],[Actual Result]],"PASS","FAIL"))) | H7: Vacation category
A8: T050 | B8: Inventory | C8: TEST-INV-SPOIL | E8: 3 | F8: =_xlfn.SWITCH(tblTesting[[#This Row],[Test ID]],"T020",_xlfn.XLOOKUP(tblTesting[[#This Row],[Test Key]],tblWeeklyMarkets[Test Key],tblWeeklyMarkets[Actual Miles],"NOT FOUND"),"T022",_xlfn.XLOOKUP(tblTesting[[#This Row],[Test Key]],tblWeeklyMarkets[Test Key],tblWeeklyMarkets[Travel Cost],"NOT FOUND"),"T030",_xlfn.XLOOKUP(tblTesting[[#This Row],[Test Key]],tblWeeklyMarkets[Test Key],tblWeeklyMarkets[Attendance Category],"NOT FOUND"),"T032",_xlfn.XLOOKUP(tblTesting[[#This Row],[Test Key]],tblWeeklyMarkets[Test Key],tblWeeklyMarkets[Attendance Category],"NOT FOUND"),"T050",_xlfn.XLOOKUP(tblTesting[[#This Row],[Test Key]],tblInventory[Test Key],tblInventory[Spoilage],"NOT FOUND"),"T052",_xlfn.XLOOKUP(tblTesting[[#This Row],[Test Key]],tblInventory[Test Key],tblInventory[Ending Inventory],"NOT FOUND"),"T060",_xlfn.XLOOKUP(tblTesting[[#This Row],[Test Key]],tblIngredientUsage[Test Key],tblIngredientUsage[Quantity Used],"NOT FOUND"),"T080",_xlfn.XLOOKUP(tblTesting[[#This Row],[Test Key]],tblProductMaster[Variation ID],tblProductMaster[Cost Complete],"NOT FOUND"),"T081",_xlfn.XLOOKUP(tblTesting[[#This Row],[Test Key]],tblProductMaster[Variation ID],tblProductMaster[Cost Complete],"NOT FOUND"),"T082",_xlfn.XLOOKUP(tblTesting[[#This Row],[Test Key]],tblProductCosts[Variation ID],tblProductCosts[Cost Review Status],"NOT FOUND"),"TEST NOT DEFINED") | G8: =IF(OR(tblTesting[[#This Row],[Actual Result]]="NOT FOUND",tblTesting[[#This Row],[Actual Result]]="TEST NOT DEFINED"),"FAIL",IF(AND(ISNUMBER(tblTesting[[#This Row],[Expected Result]]),ISNUMBER(tblTesting[[#This Row],[Actual Result]])),IF(ABS(tblTesting[[#This Row],[Expected Result]]-tblTesting[[#This Row],[Actual Result]])<0.01,"PASS","FAIL"),IF(tblTesting[[#This Row],[Expected Result]]=tblTesting[[#This Row],[Actual Result]],"PASS","FAIL"))) | H8: Auto spoilage
A9: T052 | B9: Inventory | C9: TEST-INV-CARRY | E9: 3 | F9: =_xlfn.SWITCH(tblTesting[[#This Row],[Test ID]],"T020",_xlfn.XLOOKUP(tblTesting[[#This Row],[Test Key]],tblWeeklyMarkets[Test Key],tblWeeklyMarkets[Actual Miles],"NOT FOUND"),"T022",_xlfn.XLOOKUP(tblTesting[[#This Row],[Test Key]],tblWeeklyMarkets[Test Key],tblWeeklyMarkets[Travel Cost],"NOT FOUND"),"T030",_xlfn.XLOOKUP(tblTesting[[#This Row],[Test Key]],tblWeeklyMarkets[Test Key],tblWeeklyMarkets[Attendance Category],"NOT FOUND"),"T032",_xlfn.XLOOKUP(tblTesting[[#This Row],[Test Key]],tblWeeklyMarkets[Test Key],tblWeeklyMarkets[Attendance Category],"NOT FOUND"),"T050",_xlfn.XLOOKUP(tblTesting[[#This Row],[Test Key]],tblInventory[Test Key],tblInventory[Spoilage],"NOT FOUND"),"T052",_xlfn.XLOOKUP(tblTesting[[#This Row],[Test Key]],tblInventory[Test Key],tblInventory[Ending Inventory],"NOT FOUND"),"T060",_xlfn.XLOOKUP(tblTesting[[#This Row],[Test Key]],tblIngredientUsage[Test Key],tblIngredientUsage[Quantity Used],"NOT FOUND"),"T080",_xlfn.XLOOKUP(tblTesting[[#This Row],[Test Key]],tblProductMaster[Variation ID],tblProductMaster[Cost Complete],"NOT FOUND"),"T081",_xlfn.XLOOKUP(tblTesting[[#This Row],[Test Key]],tblProductMaster[Variation ID],tblProductMaster[Cost Complete],"NOT FOUND"),"T082",_xlfn.XLOOKUP(tblTesting[[#This Row],[Test Key]],tblProductCosts[Variation ID],tblProductCosts[Cost Review Status],"NOT FOUND"),"TEST NOT DEFINED") | G9: =IF(OR(tblTesting[[#This Row],[Actual Result]]="NOT FOUND",tblTesting[[#This Row],[Actual Result]]="TEST NOT DEFINED"),"FAIL",IF(AND(ISNUMBER(tblTesting[[#This Row],[Expected Result]]),ISNUMBER(tblTesting[[#This Row],[Actual Result]])),IF(ABS(tblTesting[[#This Row],[Expected Result]]-tblTesting[[#This Row],[Actual Result]])<0.01,"PASS","FAIL"),IF(tblTesting[[#This Row],[Expected Result]]=tblTesting[[#This Row],[Actual Result]],"PASS","FAIL"))) | H9: Carry-forward ending inventory
A10: T060 | B10: Ingredient Usage | C10: TEST-USAGE-1 | E10: 8 | F10: =_xlfn.SWITCH(tblTesting[[#This Row],[Test ID]],"T020",_xlfn.XLOOKUP(tblTesting[[#This Row],[Test Key]],tblWeeklyMarkets[Test Key],tblWeeklyMarkets[Actual Miles],"NOT FOUND"),"T022",_xlfn.XLOOKUP(tblTesting[[#This Row],[Test Key]],tblWeeklyMarkets[Test Key],tblWeeklyMarkets[Travel Cost],"NOT FOUND"),"T030",_xlfn.XLOOKUP(tblTesting[[#This Row],[Test Key]],tblWeeklyMarkets[Test Key],tblWeeklyMarkets[Attendance Category],"NOT FOUND"),"T032",_xlfn.XLOOKUP(tblTesting[[#This Row],[Test Key]],tblWeeklyMarkets[Test Key],tblWeeklyMarkets[Attendance Category],"NOT FOUND"),"T050",_xlfn.XLOOKUP(tblTesting[[#This Row],[Test Key]],tblInventory[Test Key],tblInventory[Spoilage],"NOT FOUND"),"T052",_xlfn.XLOOKUP(tblTesting[[#This Row],[Test Key]],tblInventory[Test Key],tblInventory[Ending Inventory],"NOT FOUND"),"T060",_xlfn.XLOOKUP(tblTesting[[#This Row],[Test Key]],tblIngredientUsage[Test Key],tblIngredientUsage[Quantity Used],"NOT FOUND"),"T080",_xlfn.XLOOKUP(tblTesting[[#This Row],[Test Key]],tblProductMaster[Variation ID],tblProductMaster[Cost Complete],"NOT FOUND"),"T081",_xlfn.XLOOKUP(tblTesting[[#This Row],[Test Key]],tblProductMaster[Variation ID],tblProductMaster[Cost Complete],"NOT FOUND"),"T082",_xlfn.XLOOKUP(tblTesting[[#This Row],[Test Key]],tblProductCosts[Variation ID],tblProductCosts[Cost Review Status],"NOT FOUND"),"TEST NOT DEFINED") | G10: =IF(OR(tblTesting[[#This Row],[Actual Result]]="NOT FOUND",tblTesting[[#This Row],[Actual Result]]="TEST NOT DEFINED"),"FAIL",IF(AND(ISNUMBER(tblTesting[[#This Row],[Expected Result]]),ISNUMBER(tblTesting[[#This Row],[Actual Result]])),IF(ABS(tblTesting[[#This Row],[Expected Result]]-tblTesting[[#This Row],[Actual Result]])<0.01,"PASS","FAIL"),IF(tblTesting[[#This Row],[Expected Result]]=tblTesting[[#This Row],[Actual Result]],"PASS","FAIL"))) | H10: 20 x 0.4
A11: T080 | B11: Product Setup | C11: TEST-VAR001 | E11: Yes | F11: =_xlfn.SWITCH(tblTesting[[#This Row],[Test ID]],"T020",_xlfn.XLOOKUP(tblTesting[[#This Row],[Test Key]],tblWeeklyMarkets[Test Key],tblWeeklyMarkets[Actual Miles],"NOT FOUND"),"T022",_xlfn.XLOOKUP(tblTesting[[#This Row],[Test Key]],tblWeeklyMarkets[Test Key],tblWeeklyMarkets[Travel Cost],"NOT FOUND"),"T030",_xlfn.XLOOKUP(tblTesting[[#This Row],[Test Key]],tblWeeklyMarkets[Test Key],tblWeeklyMarkets[Attendance Category],"NOT FOUND"),"T032",_xlfn.XLOOKUP(tblTesting[[#This Row],[Test Key]],tblWeeklyMarkets[Test Key],tblWeeklyMarkets[Attendance Category],"NOT FOUND"),"T050",_xlfn.XLOOKUP(tblTesting[[#This Row],[Test Key]],tblInventory[Test Key],tblInventory[Spoilage],"NOT FOUND"),"T052",_xlfn.XLOOKUP(tblTesting[[#This Row],[Test Key]],tblInventory[Test Key],tblInventory[Ending Inventory],"NOT FOUND"),"T060",_xlfn.XLOOKUP(tblTesting[[#This Row],[Test Key]],tblIngredientUsage[Test Key],tblIngredientUsage[Quantity Used],"NOT FOUND"),"T080",_xlfn.XLOOKUP(tblTesting[[#This Row],[Test Key]],tblProductMaster[Variation ID],tblProductMaster[Cost Complete],"NOT FOUND"),"T081",_xlfn.XLOOKUP(tblTesting[[#This Row],[Test Key]],tblProductMaster[Variation ID],tblProductMaster[Cost Complete],"NOT FOUND"),"T082",_xlfn.XLOOKUP(tblTesting[[#This Row],[Test Key]],tblProductCosts[Variation ID],tblProductCosts[Cost Review Status],"NOT FOUND"),"TEST NOT DEFINED") | G11: =IF(OR(tblTesting[[#This Row],[Actual Result]]="NOT FOUND",tblTesting[[#This Row],[Actual Result]]="TEST NOT DEFINED"),"FAIL",IF(AND(ISNUMBER(tblTesting[[#This Row],[Expected Result]]),ISNUMBER(tblTesting[[#This Row],[Actual Result]])),IF(ABS(tblTesting[[#This Row],[Expected Result]]-tblTesting[[#This Row],[Actual Result]])<0.01,"PASS","FAIL"),IF(tblTesting[[#This Row],[Expected Result]]=tblTesting[[#This Row],[Actual Result]],"PASS","FAIL"))) | H11: Cost complete
A12: T081 | B12: Product Setup | C12: TEST-VAR002 | E12: No | F12: =_xlfn.SWITCH(tblTesting[[#This Row],[Test ID]],"T020",_xlfn.XLOOKUP(tblTesting[[#This Row],[Test Key]],tblWeeklyMarkets[Test Key],tblWeeklyMarkets[Actual Miles],"NOT FOUND"),"T022",_xlfn.XLOOKUP(tblTesting[[#This Row],[Test Key]],tblWeeklyMarkets[Test Key],tblWeeklyMarkets[Travel Cost],"NOT FOUND"),"T030",_xlfn.XLOOKUP(tblTesting[[#This Row],[Test Key]],tblWeeklyMarkets[Test Key],tblWeeklyMarkets[Attendance Category],"NOT FOUND"),"T032",_xlfn.XLOOKUP(tblTesting[[#This Row],[Test Key]],tblWeeklyMarkets[Test Key],tblWeeklyMarkets[Attendance Category],"NOT FOUND"),"T050",_xlfn.XLOOKUP(tblTesting[[#This Row],[Test Key]],tblInventory[Test Key],tblInventory[Spoilage],"NOT FOUND"),"T052",_xlfn.XLOOKUP(tblTesting[[#This Row],[Test Key]],tblInventory[Test Key],tblInventory[Ending Inventory],"NOT FOUND"),"T060",_xlfn.XLOOKUP(tblTesting[[#This Row],[Test Key]],tblIngredientUsage[Test Key],tblIngredientUsage[Quantity Used],"NOT FOUND"),"T080",_xlfn.XLOOKUP(tblTesting[[#This Row],[Test Key]],tblProductMaster[Variation ID],tblProductMaster[Cost Complete],"NOT FOUND"),"T081",_xlfn.XLOOKUP(tblTesting[[#This Row],[Test Key]],tblProductMaster[Variation ID],tblProductMaster[Cost Complete],"NOT FOUND"),"T082",_xlfn.XLOOKUP(tblTesting[[#This Row],[Test Key]],tblProductCosts[Variation ID],tblProductCosts[Cost Review Status],"NOT FOUND"),"TEST NOT DEFINED") | G12: =IF(OR(tblTesting[[#This Row],[Actual Result]]="NOT FOUND",tblTesting[[#This Row],[Actual Result]]="TEST NOT DEFINED"),"FAIL",IF(AND(ISNUMBER(tblTesting[[#This Row],[Expected Result]]),ISNUMBER(tblTesting[[#This Row],[Actual Result]])),IF(ABS(tblTesting[[#This Row],[Expected Result]]-tblTesting[[#This Row],[Actual Result]])<0.01,"PASS","FAIL"),IF(tblTesting[[#This Row],[Expected Result]]=tblTesting[[#This Row],[Actual Result]],"PASS","FAIL"))) | H12: Missing cost
A13: T082 | B13: Product Cost | C13: TEST-VAR003 | E13: REVIEW COST | F13: =_xlfn.SWITCH(tblTesting[[#This Row],[Test ID]],"T020",_xlfn.XLOOKUP(tblTesting[[#This Row],[Test Key]],tblWeeklyMarkets[Test Key],tblWeeklyMarkets[Actual Miles],"NOT FOUND"),"T022",_xlfn.XLOOKUP(tblTesting[[#This Row],[Test Key]],tblWeeklyMarkets[Test Key],tblWeeklyMarkets[Travel Cost],"NOT FOUND"),"T030",_xlfn.XLOOKUP(tblTesting[[#This Row],[Test Key]],tblWeeklyMarkets[Test Key],tblWeeklyMarkets[Attendance Category],"NOT FOUND"),"T032",_xlfn.XLOOKUP(tblTesting[[#This Row],[Test Key]],tblWeeklyMarkets[Test Key],tblWeeklyMarkets[Attendance Category],"NOT FOUND"),"T050",_xlfn.XLOOKUP(tblTesting[[#This Row],[Test Key]],tblInventory[Test Key],tblInventory[Spoilage],"NOT FOUND"),"T052",_xlfn.XLOOKUP(tblTesting[[#This Row],[Test Key]],tblInventory[Test Key],tblInventory[Ending Inventory],"NOT FOUND"),"T060",_xlfn.XLOOKUP(tblTesting[[#This Row],[Test Key]],tblIngredientUsage[Test Key],tblIngredientUsage[Quantity Used],"NOT FOUND"),"T080",_xlfn.XLOOKUP(tblTesting[[#This Row],[Test Key]],tblProductMaster[Variation ID],tblProductMaster[Cost Complete],"NOT FOUND"),"T081",_xlfn.XLOOKUP(tblTesting[[#This Row],[Test Key]],tblProductMaster[Variation ID],tblProductMaster[Cost Complete],"NOT FOUND"),"T082",_xlfn.XLOOKUP(tblTesting[[#This Row],[Test Key]],tblProductCosts[Variation ID],tblProductCosts[Cost Review Status],"NOT FOUND"),"TEST NOT DEFINED") | G13: =IF(OR(tblTesting[[#This Row],[Actual Result]]="NOT FOUND",tblTesting[[#This Row],[Actual Result]]="TEST NOT DEFINED"),"FAIL",IF(AND(ISNUMBER(tblTesting[[#This Row],[Expected Result]]),ISNUMBER(tblTesting[[#This Row],[Actual Result]])),IF(ABS(tblTesting[[#This Row],[Expected Result]]-tblTesting[[#This Row],[Actual Result]])<0.01,"PASS","FAIL"),IF(tblTesting[[#This Row],[Expected Result]]=tblTesting[[#This Row],[Actual Result]],"PASS","FAIL"))) | H13: Old cost

Sheet Data_Dictionary
A1: DATA DICTIONARY
A3: Table | B3: Column | C3: Data Type | D3: Required | E3: Formula | F3: Description
A4: tblWeeklyMarkets | B4: Test Key | C4: Text | D4: No | E4: No | F4: Test fixture identifier
A5: tblWeeklyMarkets | B5: Market Date | C5: Date | D5: Yes | E5: No | F5: Actual attended/planned date
A6: tblWeeklyMarkets | B6: Market | C6: Text | D6: Yes | E6: No | F6: Market name
A7: tblWeeklyMarkets | B7: Market Status | C7: Text | D7: Yes | E7: No | F7: Single user-facing status
A8: tblWeeklyMarkets | B8: Market Day Score | C8: Text | D8: No | E8: No | F8: Excellent to Terrible
A9: tblWeeklyMarkets | B9: Notes | C9: Text | D9: No | E9: No | F9: Optional notes
A10: tblWeeklyMarkets | B10: Override Miles | C10: Number | D10: No | E10: No | F10: Optional exception
A11: tblWeeklyMarkets | B11: Attendance Category | C11: Text | D11: No | E11: Yes | F11: Derived
A12: tblWeeklyMarkets | B12: Market Match Count | C12: Number | D12: No | E12: Yes | F12: Effective-date matches
A13: tblWeeklyMarkets | B13: Market Fee | C13: Currency | D13: No | E13: Yes | F13: Date-effective default
A14: tblWeeklyMarkets | B14: Actual Miles | C14: Number | D14: No | E14: Yes | F14: Override or default
... A49: tblProductSetup | B49: Test Record | C49: Yes/No | D49: Yes | E49: No | F49: Test isolation

Sheet Settings
A1: SETTINGS
A3: Setting | B3: Value
A4: Mileage Rate | B4: 0.67
A5: Market Ranking Minimum Visits | B5: 5
A6: Week Starts On | B6: Monday
A7: Testing Mode | B7: No
A8: Weekly Profit Goal | B8: 300
A9: Safety Stock % | B9: 0.2

Sheet Market_Master
A1: MARKET MASTER
A3: Market | B3: Start Date | C3: End Date | D3: Market Fee | E3: Default Round Trip Miles | F3: Default Travel Minutes | G3: Active | H3: Invalid Date Range | I3: Fee Validation | J3: Conflict Details | K3: Overlap Count | L3: Test Record
A4: TEST-ORLANDO | B4: 46023 | D4: 40 | E4: 84 | F4: 90 | G4: =IF(OR(tblMarketMaster[[#This Row],[End Date]]="",tblMarketMaster[[#This Row],[End Date]]>=TODAY()),"Active","Expired") | H4: =IF(OR(tblMarketMaster[[#This Row],[Start Date]]="",tblMarketMaster[[#This Row],[End Date]]=""),"",IF(tblMarketMaster[[#This Row],[End Date]]<tblMarketMaster[[#This Row],[Start Date]],"INVALID","OK")) | I4: =IF(tblMarketMaster[[#This Row],[Market Fee]]="","MISSING FEE",IF(NOT(ISNUMBER(tblMarketMaster[[#This Row],[Market Fee]])),"INVALID FEE",IF(tblMarketMaster[[#This Row],[Market Fee]]<0,"INVALID FEE","OK"))) | J4: =_xlfn.LET(M,tblMarketMaster[[#This Row],[Market]],S,tblMarketMaster[[#This Row],[Start Date]],E,IF(tblMarketMaster[[#This Row],[End Date]]="",DATE(9999,12,31),tblMarketMaster[[#This Row],[End Date]]),OM,tblMarketMaster[Market],OS,tblMarketMaster[Start Date],OE,IF(tblMarketMaster[End Date]="",DATE(9999,12,31),tblMarketMaster[End Date]),OF,tblMarketMaster[Market Fee],Matches,(OM=M)*(OS<=E)*(OE>=S)*(ROW(OM)<>ROW()),IFERROR(_xlfn.TEXTJOIN(CHAR(10),TRUE,_xlfn._xlws.FILTER(OM&" | $"&TEXT(OF,"0.00")&" | "&TEXT(OS,"m/d/yyyy")&" to "&IF(OE=DATE(9999,12,31),"Current",TEXT(OE,"m/d/yyyy")),Matches)),"")) | K4: =IF(tblMarketMaster[[#This Row],[Conflict Details]]="",0,LEN(tblMarketMaster[[#This Row],[Conflict Details]])-LEN(SUBSTITUTE(tblMarketMaster[[#This Row],[Conflict Details]],CHAR(10),""))+1) | L4: Yes
A5: TEST-HAINES | B5: 46023 | D5: 25 | E5: 18 | F5: 25 | G5: =IF(OR(tblMarketMaster[[#This Row],[End Date]]="",tblMarketMaster[[#This Row],[End Date]]>=TODAY()),"Active","Expired") | H5: =IF(OR(tblMarketMaster[[#This Row],[Start Date]]="",tblMarketMaster[[#This Row],[End Date]]=""),"",IF(tblMarketMaster[[#This Row],[End Date]]<tblMarketMaster[[#This Row],[Start Date]],"INVALID","OK")) | I5: =IF(tblMarketMaster[[#This Row],[Market Fee]]="","MISSING FEE",IF(NOT(ISNUMBER(tblMarketMaster[[#This Row],[Market Fee]])),"INVALID FEE",IF(tblMarketMaster[[#This Row],[Market Fee]]<0,"INVALID FEE","OK"))) | J5: =_xlfn.LET(M,tblMarketMaster[[#This Row],[Market]],S,tblMarketMaster[[#This Row],[Start Date]],E,IF(tblMarketMaster[[#This Row],[End Date]]="",DATE(9999,12,31),tblMarketMaster[[#This Row],[End Date]]),OM,tblMarketMaster[Market],OS,tblMarketMaster[Start Date],OE,IF(tblMarketMaster[End Date]="",DATE(9999,12,31),tblMarketMaster[End Date]),OF,tblMarketMaster[Market Fee],Matches,(OM=M)*(OS<=E)*(OE>=S)*(ROW(OM)<>ROW()),IFERROR(_xlfn.TEXTJOIN(CHAR(10),TRUE,_xlfn._xlws.FILTER(OM&" | $"&TEXT(OF,"0.00")&" | "&TEXT(OS,"m/d/yyyy")&" to "&IF(OE=DATE(9999,12,31),"Current",TEXT(OE,"m/d/yyyy")),Matches)),"")) | K5: =IF(tblMarketMaster[[#This Row],[Conflict Details]]="",0,LEN(tblMarketMaster[[#This Row],[Conflict Details]])-LEN(SUBSTITUTE(tblMarketMaster[[#This Row],[Conflict Details]],CHAR(10),""))+1) | L5: Yes

Sheet Product_Setup_Data
A1: PRODUCT SETUP DATA
A3: Variation ID | B3: Shelf Stable | C3: Spoils If Unsold | D3: Product Group | E3: Product Active | F3: Notes | G3: Test Record
A4: TEST-VAR001 | B4: Yes | C4: Yes | D4: Jam | E4: Yes | F4: Fixture | G4: Yes
A5: TEST-VAR002 | B5: Yes | C5: No | D5: Jam | E5: Yes | F5: Fixture | G5: Yes
A6: TEST-VAR003 | B6: No | C6: Yes | D6: Fresh | E6: Yes | F6: Fixture | G6: Yes
A7: TEST-VAR004 | B7: Yes | C7: Yes | D7: Honey | E7: Yes | F7: Fixture | G7: Yes

Sheet Recipe_Master
A1: RECIPE MASTER
A3: Recipe ID | B3: Recipe Name | C3: Recipe Active | D3: Notes | E3: Test Record
A4: TEST-R001 | B4: Test Strawberry Jam Base | C4: Yes | D4: Fixture | E4: Yes
A5: TEST-R002 | B5: Test Bread Base | C5: Yes | D5: Fixture | E5: Yes

Sheet Product_Recipe_Map
A1: PRODUCT RECIPE MAPPING
A3: Variation ID | B3: Recipe ID | C3: Test Record
A4: TEST-VAR001 | B4: TEST-R001 | C4: Yes
A5: TEST-VAR002 | B5: TEST-R001 | C5: Yes
A6: TEST-VAR003 | B6: TEST-R002 | C6: Yes

Sheet Recipe_Ingredients
A1: RECIPE INGREDIENTS
A3: Recipe ID | B3: Ingredient | C3: Quantity Per Item | D3: Unit | E3: Test Record
A4: TEST-R001 | B4: Strawberries | C4: 0.4 | D4: lb | E4: Yes
A5: TEST-R001 | B5: Sugar | C5: 0.2 | D5: lb | E5: Yes
A6: TEST-R001 | B6: Jar | C6: 1 | D6: each | E6: Yes
A7: TEST-R002 | B7: Flour | C7: 0.5 | D7: lb | E7: Yes

Sheet Product_Costs
A1: PRODUCT COSTS
A3: Variation ID | B3: Effective Date | C3: Manual Cost | D3: Cost Review Status | E3: Test Record
A4: TEST-VAR001 | B4: 46023 | C4: 2.15 | D4: OK | E4: Yes
A5: TEST-VAR003 | B5: 45658 | C5: 1.5 | D5: REVIEW COST | E5: Yes

Sheet Ingredient_Cost_History
A1: INGREDIENT COST HISTORY
A3: Ingredient | B3: Effective Date | C3: Cost Per Unit | D3: Unit | E3: Test Record
A4: Sugar | B4: 45658 | C4: 0.75 | D4: lb | E4: Yes
A5: Sugar | B5: 46023 | C5: 0.82 | D5: lb | E5: Yes
A6: Strawberries | B6: 46023 | C6: 2 | D6: lb | E6: Yes

Sheet Business_Exceptions
A1: BUSINESS EXCEPTIONS
A3: Start Date | B3: End Date | C3: Exception Type | D3: Applies To | E3: Market | F3: Notes | G3: Business Impact | H3: Date Validation | I3: Test Record
A4: 46034 | B4: 46040 | C4: Vacation | D4: Entire Business | F4: Fixture | G4: No Sales Expected | H4: =IF(tblBusinessExceptions[[#This Row],[End Date]]<tblBusinessExceptions[[#This Row],[Start Date]],"INVALID","OK") | I4: Yes

Sheet Inventory
A1: INVENTORY
A3: Test Key | B3: Variation ID | C3: Inventory Date | D3: Beginning Inventory | E3: Produced | F3: Sold | G3: Samples | H3: Available | I3: Inventory Variance | J3: Spoilage | K3: Ending Inventory | L3: Validation | M3: Test Record
A4: TEST-INV-SPOIL | B4: TEST-VAR001 | C4: 46027 | D4: 0 | E4: 20 | F4: 15 | G4: 2 | H4: =tblInventory[[#This Row],[Beginning Inventory]]+tblInventory[[#This Row],[Produced]] | I4: =tblInventory[[#This Row],[Available]]-tblInventory[[#This Row],[Sold]]-tblInventory[[#This Row],[Samples]] | J4: =IF(_xlfn.XLOOKUP(tblInventory[[#This Row],[Variation ID]],tblProductSetup[Variation ID],tblProductSetup[Spoils If Unsold],"Yes")="Yes",MAX(0,tblInventory[[#This Row],[Inventory Variance]]),0) | K4: =IF(_xlfn.XLOOKUP(tblInventory[[#This Row],[Variation ID]],tblProductSetup[Variation ID],tblProductSetup[Spoils If Unsold],"Yes")="Yes",0,MAX(0,tblInventory[[#This Row],[Inventory Variance]]-tblInventory[[#This Row],[Spoilage]])) | L4: =IF(tblInventory[[#This Row],[Inventory Variance]]<0,"ERROR: SOLD/SAMPLES EXCEED AVAILABLE","OK") | M4: Yes
A5: TEST-INV-CARRY | B5: TEST-VAR002 | C5: 46027 | D5: 0 | E5: 20 | F5: 15 | G5: 2 | H5: =tblInventory[[#This Row],[Beginning Inventory]]+tblInventory[[#This Row],[Produced]] | I5: =tblInventory[[#This Row],[Available]]-tblInventory[[#This Row],[Sold]]-tblInventory[[#This Row],[Samples]] | J5: =IF(_xlfn.XLOOKUP(tblInventory[[#This Row],[Variation ID]],tblProductSetup[Variation ID],tblProductSetup[Spoils If Unsold],"Yes")="Yes",MAX(0,tblInventory[[#This Row],[Inventory Variance]]),0) | K5: =IF(_xlfn.XLOOKUP(tblInventory[[#This Row],[Variation ID]],tblProductSetup[Variation ID],tblProductSetup[Spoils If Unsold],"Yes")="Yes",0,MAX(0,tblInventory[[#This Row],[Inventory Variance]]-tblInventory[[#This Row],[Spoilage]])) | L5: =IF(tblInventory[[#This Row],[Inventory Variance]]<0,"ERROR: SOLD/SAMPLES EXCEED AVAILABLE","OK") | M5: Yes

Sheet Ingredient_Purchases

Sheet Expenses

Sheet Market_Rankings
A1: MARKET RANKINGS
A3: Market | B3: Visit Count | C3: Eligibility | D3: Lifetime Avg Profit | E3: Business Score | F3: Personal Score | G3: Business Rank | H3: Personal Rank | I3: Confidence | J3: Ranking Reason | K3: Test Record
A4: TEST-ORLANDO | B4: 5 | C4: =IF(tblMarketRankings[[#This Row],[Visit Count]]>=MarketRankingMinimumVisits,"Eligible","Not Ranked") | D4: 200 | E4: 85 | F4: 80 | G4: =IF(OR(tblMarketRankings[[#This Row],[Eligibility]]<>"Eligible",tblMarketRankings[[#This Row],[Test Record]]<>"No"),"N/R",1+SUMPRODUCT(--(tblMarketRankings[Eligibility]="Eligible"),--(tblMarketRankings[Test Record]="No"),--(((tblMarketRankings[Business Score]>tblMarketRankings[[#This Row],[Business Score]])+((tblMarketRankings[Business Score]=tblMarketRankings[[#This Row],[Business Score]])*(tblMarketRankings[Lifetime Avg Profit]>tblMarketRankings[[#This Row],[Lifetime Avg Profit]]))+((tblMarketRankings[Business Score]=tblMarketRankings[[#This Row],[Business Score]])*(tblMarketRankings[Lifetime Avg Profit]=tblMarketRankings[[#This Row],[Lifetime Avg Profit]])*(tblMarketRankings[Visit Count]>tblMarketRankings[[#This Row],[Visit Count]]))+((tblMarketRankings[Business Score]=tblMarketRankings[[#This Row],[Business Score]])*(tblMarketRankings[Lifetime Avg Profit]=tblMarketRankings[[#This Row],[Lifetime Avg Profit]])*(tblMarketRankings[Visit Count]=tblMarketRankings[[#This Row],[Visit Count]])*(tblMarketRankings[Market]<tblMarketRankings[[#This Row],[Market]])))>0))) | H4: =IF(OR(tblMarketRankings[[#This Row],[Eligibility]]<>"Eligible",tblMarketRankings[[#This Row],[Test Record]]<>"No"),"N/R",1+SUMPRODUCT(--(tblMarketRankings[Eligibility]="Eligible"),--(tblMarketRankings[Test Record]="No"),--(((tblMarketRankings[Personal Score]>tblMarketRankings[[#This Row],[Personal Score]])+((tblMarketRankings[Personal Score]=tblMarketRankings[[#This Row],[Personal Score]])*(tblMarketRankings[Lifetime Avg Profit]>tblMarketRankings[[#This Row],[Lifetime Avg Profit]]))+((tblMarketRankings[Personal Score]=tblMarketRankings[[#This Row],[Personal Score]])*(tblMarketRankings[Lifetime Avg Profit]=tblMarketRankings[[#This Row],[Lifetime Avg Profit]])*(tblMarketRankings[Visit Count]>tblMarketRankings[[#This Row],[Visit Count]]))+((tblMarketRankings[Personal Score]=tblMarketRankings[[#This Row],[Personal Score]])*(tblMarketRankings[Lifetime Avg Profit]=tblMarketRankings[[#This Row],[Lifetime Avg Profit]])*(tblMarketRankings[Visit Count]=tblMarketRankings[[#This Row],[Visit Count]])*(tblMarketRankings[Market]<tblMarketRankings[[#This Row],[Market]])))>0))) | I4: =IF(tblMarketRankings[[#This Row],[Visit Count]]<MarketRankingMinimumVisits,"Insufficient Data",IF(tblMarketRankings[[#This Row],[Visit Count]]<10,"Medium","High")) | J4: =IF(tblMarketRankings[[#This Row],[Test Record]]="Yes","Test Record",IF(tblMarketRankings[[#This Row],[Visit Count]]<MarketRankingMinimumVisits,"Needs "&(MarketRankingMinimumVisits-tblMarketRankings[[#This Row],[Visit Count]])&" More Visits","Eligible")) | K4: Yes
A5: TEST-HAINES | B5: 5 | C5: =IF(tblMarketRankings[[#This Row],[Visit Count]]>=MarketRankingMinimumVisits,"Eligible","Not Ranked") | D5: 200 | E5: 85 | F5: 80 | G5: =IF(OR(tblMarketRankings[[#This Row],[Eligibility]]<>"Eligible",tblMarketRankings[[#This Row],[Test Record]]<>"No"),"N/R",1+SUMPRODUCT(--(tblMarketRankings[Eligibility]="Eligible"),--(tblMarketRankings[Test Record]="No"),--(((tblMarketRankings[Business Score]>tblMarketRankings[[#This Row],[Business Score]])+((tblMarketRankings[Business Score]=tblMarketRankings[[#This Row],[Business Score]])*(tblMarketRankings[Lifetime Avg Profit]>tblMarketRankings[[#This Row],[Lifetime Avg Profit]]))+((tblMarketRankings[Business Score]=tblMarketRankings[[#This Row],[Business Score]])*(tblMarketRankings[Lifetime Avg Profit]=tblMarketRankings[[#This Row],[Lifetime Avg Profit]])*(tblMarketRankings[Visit Count]>tblMarketRankings[[#This Row],[Visit Count]]))+((tblMarketRankings[Business Score]=tblMarketRankings[[#This Row],[Business Score]])*(tblMarketRankings[Lifetime Avg Profit]=tblMarketRankings[[#This Row],[Lifetime Avg Profit]])*(tblMarketRankings[Visit Count]=tblMarketRankings[[#This Row],[Visit Count]])*(tblMarketRankings[Market]<tblMarketRankings[[#This Row],[Market]])))>0))) | H5: =IF(OR(tblMarketRankings[[#This Row],[Eligibility]]<>"Eligible",tblMarketRankings[[#This Row],[Test Record]]<>"No"),"N/R",1+SUMPRODUCT(--(tblMarketRankings[Eligibility]="Eligible"),--(tblMarketRankings[Test Record]="No"),--(((tblMarketRankings[Personal Score]>tblMarketRankings[[#This Row],[Personal Score]])+((tblMarketRankings[Personal Score]=tblMarketRankings[[#This Row],[Personal Score]])*(tblMarketRankings[Lifetime Avg Profit]>tblMarketRankings[[#This Row],[Lifetime Avg Profit]]))+((tblMarketRankings[Personal Score]=tblMarketRankings[[#This Row],[Personal Score]])*(tblMarketRankings[Lifetime Avg Profit]=tblMarketRankings[[#This Row],[Lifetime Avg Profit]])*(tblMarketRankings[Visit Count]>tblMarketRankings[[#This Row],[Visit Count]]))+((tblMarketRankings[Personal Score]=tblMarketRankings[[#This Row],[Personal Score]])*(tblMarketRankings[Lifetime Avg Profit]=tblMarketRankings[[#This Row],[Lifetime Avg Profit]])*(tblMarketRankings[Visit Count]=tblMarketRankings[[#This Row],[Visit Count]])*(tblMarketRankings[Market]<tblMarketRankings[[#This Row],[Market]])))>0))) | I5: =IF(tblMarketRankings[[#This Row],[Visit Count]]<MarketRankingMinimumVisits,"Insufficient Data",IF(tblMarketRankings[[#This Row],[Visit Count]]<10,"Medium","High")) | J5: =IF(tblMarketRankings[[#This Row],[Test Record]]="Yes","Test Record",IF(tblMarketRankings[[#This Row],[Visit Count]]<MarketRankingMinimumVisits,"Needs "&(MarketRankingMinimumVisits-tblMarketRankings[[#This Row],[Visit Count]])&" More Visits","Eligible")) | K5: Yes

Sheet Product_Rankings
A1: PRODUCT RANKINGS
A3: Variation ID | B3: Product Name | C3: Annual Profit | D3: Profit Rank | E3: Test Record
A4: TEST-VAR001 | B4: Test Strawberry Jam 8 oz | C4: 500 | D4: 1 | E4: Yes

Sheet Error_Log
A1: ERROR LOG
A3: Date Found | B3: Error Type | C3: Source | D3: Reference | E3: Description | F3: Severity | G3: Status | H3: Resolution Notes
A4: 46027 | B4: Fixture | C4: TESTING | D4: TEST-001 | E4: Test error-log fixture | F4: Low | G4: Resolved | H4: Fixture only

Sheet Workbook_Version
A1: WORKBOOK VERSION
A3: Version | B3: Date | C3: Change | D3: Tested | E3: Approved By
A4: 1.0 | B4: 46290 | C4: Initial governed template | D4: Yes

Sheet Square_Catalog
A1: SQUARE CATALOG (QUERY OUTPUT)
A3: Variation ID | B3: Item ID | C3: Product Name | D3: Variation Name | E3: SKU | F3: First Seen Date | G3: Last Seen Date | H3: Active In Square | I3: Test Record
A4: TEST-VAR001 | B4: TEST-ITEM1 | C4: Test Strawberry Jam | D4: 8 oz | E4: T-SJ8 | F4: 45809 | G4: 46027 | H4: Yes | I4: Yes
A5: TEST-VAR002 | B5: TEST-ITEM1 | C5: Test Strawberry Jam | D5: 16 oz | E5: T-SJ16 | F5: 45809 | G5: 46027 | H5: Yes | I5: Yes
A6: TEST-VAR003 | B6: TEST-ITEM2 | C6: Test Fresh Bread | D6: Regular | E6: T-BRD | F6: 45839 | G6: 46027 | H6: Yes | I6: Yes
A7: TEST-VAR004 | B7: TEST-ITEM3 | C7: Test Hot Honey | D7: Regular | E7: T-HNY | F7: 45870 | G7: 46027 | H7: Yes | I7: Yes

Sheet Sales_Data
A1: SALES DATA (QUERY OUTPUT)
A3: Sale Timestamp | B3: Variation ID | C3: Product Name | D3: Quantity Sold | E3: Gross Sales | F3: Effective Product Cost | G3: COGS | H3: Square Fee | I3: Source File | J3: Duplicate Key | K3: Test Record
A4: 46027.417 | B4: TEST-VAR001 | C4: Test Strawberry Jam 8 oz | D4: 15 | E4: 150 | F4: 2.15 | G4: =tblSalesData[[#This Row],[Quantity Sold]]*tblSalesData[[#This Row],[Effective Product Cost]] | H4: 4.5 | I4: test_week1.csv | J4: TX1-L1 | K4: Yes

Sheet Import_Log
A1: IMPORT LOG
A3: Import Timestamp | B3: Source File | C3: Imported By | D3: Records Imported | E3: Status | F3: Test Record
A4: 46028.333 | B4: test_week1.csv | C4: Test User | D4: 1 | E4: Success | F4: Yes

Sheet Ingredient_Usage
A1: INGREDIENT USAGE
A3: Test Key | B3: Usage Date | C3: Recipe ID | D3: Variation ID | E3: Ingredient | F3: Quantity Produced | G3: Quantity Per Item | H3: Quantity Used | I3: Unit Cost | J3: Usage Cost | K3: Test Record
A4: TEST-USAGE-1 | B4: 46027 | C4: TEST-R001 | D4: TEST-VAR001 | E4: Strawberries | F4: 20 | G4: 0.4 | H4: =tblIngredientUsage[[#This Row],[Quantity Produced]]*tblIngredientUsage[[#This Row],[Quantity Per Item]] | I4: =_xlfn.LET(Ing,tblIngredientUsage[[#This Row],[Ingredient]],Dt,tblIngredientUsage[[#This Row],[Usage Date]],EffDate,IFERROR(_xlfn.MAXIFS(tblIngredientCostHistory[Effective Date],tblIngredientCostHistory[Ingredient],Ing,tblIngredientCostHistory[Effective Date],"<="&Dt),0),IF(EffDate=0,"",_xlfn.XLOOKUP(1,(tblIngredientCostHistory[Ingredient]=Ing)*(tblIngredientCostHistory[Effective Date]=EffDate),tblIngredientCostHistory[Cost Per Unit],""))) | J4: =IFERROR(tblIngredientUsage[[#This Row],[Quantity Used]]*tblIngredientUsage[[#This Row],[Unit Cost]],0) | K4: Yes

Sheet Executive_Dashboard
A1: EXECUTIVE DASHBOARD
A3: Weekly | D3: Monthly | G3: Year to Date
A4: Weekly Revenue | B4: =SUMIFS(tblSalesData[Gross Sales],tblSalesData[Sale Timestamp],">="&CurrentWeekStart,tblSalesData[Sale Timestamp],"<"&CurrentWeekEnd+1,tblSalesData[Test Record],"No") | D4: Monthly Revenue | E4: =SUMIFS(tblSalesData[Gross Sales],tblSalesData[Sale Timestamp],">="&CurrentMonthStart,tblSalesData[Sale Timestamp],"<"&EOMONTH(TODAY(),0)+1,tblSalesData[Test Record],"No") | G4: YTD Revenue | H4: =SUMIFS(tblSalesData[Gross Sales],tblSalesData[Sale Timestamp],">="&CurrentYearStart,tblSalesData[Sale Timestamp],"<"&TODAY()+1,tblSalesData[Test Record],"No")
A5: Weekly Profit | B5: =B4-B5-B6-B7-B8-B9 | D5: Monthly COGS | E5: =SUMIFS(tblSalesData[COGS],tblSalesData[Sale Timestamp],">="&CurrentMonthStart,tblSalesData[Sale Timestamp],"<"&EOMONTH(TODAY(),0)+1,tblSalesData[Test Record],"No") | G5: YTD COGS | H5: =SUMIFS(tblSalesData[COGS],tblSalesData[Sale Timestamp],">="&CurrentYearStart,tblSalesData[Sale Timestamp],"<"&TODAY()+1,tblSalesData[Test Record],"No")
A6: Weekly COGS | B6: =SUMIFS(tblSalesData[COGS],tblSalesData[Sale Timestamp],">="&CurrentWeekStart,tblSalesData[Sale Timestamp],"<"&CurrentWeekEnd+1,tblSalesData[Test Record],"No") | D6: Monthly Market Fees | E6: =SUMIFS(tblWeeklyMarkets[Market Fee],tblWeeklyMarkets[Market Date],">="&CurrentMonthStart,tblWeeklyMarkets[Market Date],"<"&EOMONTH(TODAY(),0)+1,tblWeeklyMarkets[Test Record],"No") | G6: YTD Market Fees | H6: =SUMIFS(tblWeeklyMarkets[Market Fee],tblWeeklyMarkets[Market Date],">="&CurrentYearStart,tblWeeklyMarkets[Market Date],"<"&TODAY()+1,tblWeeklyMarkets[Test Record],"No")
A7: Weekly Market Fees | B7: =SUMIFS(tblWeeklyMarkets[Market Fee],tblWeeklyMarkets[Market Date],">="&CurrentWeekStart,tblWeeklyMarkets[Market Date],"<="&CurrentWeekEnd,tblWeeklyMarkets[Attendance Category],"Attended",tblWeeklyMarkets[Test Record],"No") | D7: Monthly Travel | E7: =SUMIFS(tblWeeklyMarkets[Travel Cost],tblWeeklyMarkets[Market Date],">="&CurrentMonthStart,tblWeeklyMarkets[Market Date],"<"&EOMONTH(TODAY(),0)+1,tblWeeklyMarkets[Test Record],"No") | G7: YTD Travel | H7: =SUMIFS(tblWeeklyMarkets[Travel Cost],tblWeeklyMarkets[Market Date],">="&CurrentYearStart,tblWeeklyMarkets[Market Date],"<"&TODAY()+1,tblWeeklyMarkets[Test Record],"No")
A8: Weekly Travel | B8: =SUMIFS(tblWeeklyMarkets[Travel Cost],tblWeeklyMarkets[Market Date],">="&CurrentWeekStart,tblWeeklyMarkets[Market Date],"<="&CurrentWeekEnd,tblWeeklyMarkets[Test Record],"No") | D8: Monthly Square Fees | E8: =SUMIFS(tblSalesData[Square Fee],tblSalesData[Sale Timestamp],">="&CurrentMonthStart,tblSalesData[Sale Timestamp],"<"&EOMONTH(TODAY(),0)+1,tblSalesData[Test Record],"No") | G8: YTD Square Fees | H8: =SUMIFS(tblSalesData[Square Fee],tblSalesData[Sale Timestamp],">="&CurrentYearStart,tblSalesData[Sale Timestamp],"<"&TODAY()+1,tblSalesData[Test Record],"No")
A9: Weekly Square Fees | B9: =SUMIFS(tblSalesData[Square Fee],tblSalesData[Sale Timestamp],">="&CurrentWeekStart,tblSalesData[Sale Timestamp],"<"&CurrentWeekEnd+1,tblSalesData[Test Record],"No") | D9: Monthly Expenses | E9: =SUMIFS(tblExpenses[Amount],tblExpenses[Date],">="&CurrentMonthStart,tblExpenses[Date],"<"&EOMONTH(TODAY(),0)+1,tblExpenses[Test Record],"No") | G9: YTD Expenses | H9: =SUMIFS(tblExpenses[Amount],tblExpenses[Date],">="&CurrentYearStart,tblExpenses[Date],"<"&TODAY()+1,tblExpenses[Test Record],"No")
A10: Weekly Other Expenses | B10: =SUMIFS(tblExpenses[Amount],tblExpenses[Date],">="&CurrentWeekStart,tblExpenses[Date],"<="&CurrentWeekEnd,tblExpenses[Test Record],"No") | D10: Monthly Profit | E10: =E4-E5-E6-E7-E8-E9 | G10: YTD Profit | H10: =H4-H5-H6-H7-H8-H9

Sheet Data_Quality
A1: DATA QUALITY DASHBOARD
A3: Quality Area | B3: Open Issues | C3: Weight | D3: Weighted Deduction | E3: Status | F3: Test Record
A4: Imports | B4: 0 | C4: 0.3 | D4: =MIN(100,tblDataQuality[[#This Row],[Open Issues]]*25)*tblDataQuality[[#This Row],[Weight]] | E4: =IF(tblDataQuality[[#This Row],[Open Issues]]=0,"PASS","REVIEW") | F4: No
A5: Product Setup | B5: 0 | C5: 0.3 | D5: =MIN(100,tblDataQuality[[#This Row],[Open Issues]]*25)*tblDataQuality[[#This Row],[Weight]] | E5: =IF(tblDataQuality[[#This Row],[Open Issues]]=0,"PASS","REVIEW") | F5: No
A6: Inventory | B6: 0 | C6: 0.2 | D6: =MIN(100,tblDataQuality[[#This Row],[Open Issues]]*25)*tblDataQuality[[#This Row],[Weight]] | E6: =IF(tblDataQuality[[#This Row],[Open Issues]]=0,"PASS","REVIEW") | F6: No
A7: Testing | B7: 0 | C7: 0.2 | D7: =MIN(100,tblDataQuality[[#This Row],[Open Issues]]*25)*tblDataQuality[[#This Row],[Weight]] | E7: =IF(tblDataQuality[[#This Row],[Open Issues]]=0,"PASS","REVIEW") | F7: No
A10: Health Score | B10: =MAX(0,100-SUM(tblDataQuality[Weighted Deduction]))
A11: Health Status | B11: =IF(B10>=95,"Excellent",IF(B10>=85,"Good",IF(B10>=70,"Needs Review","Action Required")))

Sheet Forecasting
A1: FORECASTING
A3: Metric | B3: Current Value | C3: 4 Week Avg | D3: 8 Week Avg | E3: 13 Week Avg | F3: Next Week Forecast | G3: Next Month Forecast | H3: Confidence | I3: Test Record
A4: Revenue | B4: 1000 | C4: 950 | D4: 900 | E4: 875 | F4: =ROUND(tblForecasting[[#This Row],[4 Week Avg]]*0.5+tblForecasting[[#This Row],[8 Week Avg]]*0.3+tblForecasting[[#This Row],[13 Week Avg]]*0.2,2) | G4: =tblForecasting[[#This Row],[Next Week Forecast]]*4.345 | H4: =IF(ABS(tblForecasting[[#This Row],[4 Week Avg]]-tblForecasting[[#This Row],[13 Week Avg]])/MAX(1,tblForecasting[[#This Row],[13 Week Avg]])<=0.10,"High",IF(ABS(tblForecasting[[#This Row],[4 Week Avg]]-tblForecasting[[#This Row],[13 Week Avg]])/MAX(1,tblForecasting[[#This Row],[13 Week Avg]])<=0.25,"Medium","Low")) | I4: Yes
A5: Profit | B5: 250 | C5: 230 | D5: 215 | E5: 200 | F5: =ROUND(tblForecasting[[#This Row],[4 Week Avg]]*0.5+tblForecasting[[#This Row],[8 Week Avg]]*0.3+tblForecasting[[#This Row],[13 Week Avg]]*0.2,2) | G5: =tblForecasting[[#This Row],[Next Week Forecast]]*4.345 | H5: =IF(ABS(tblForecasting[[#This Row],[4 Week Avg]]-tblForecasting[[#This Row],[13 Week Avg]])/MAX(1,tblForecasting[[#This Row],[13 Week Avg]])<=0.10,"High",IF(ABS(tblForecasting[[#This Row],[4 Week Avg]]-tblForecasting[[#This Row],[13 Week Avg]])/MAX(1,tblForecasting[[#This Row],[13 Week Avg]])<=0.25,"Medium","Low")) | I5: Yes

Sheet Product_Scorecards
A1: PRODUCT SCORECARDS
A3: Variation ID | B3: Product Name | C3: Revenue | D3: COGS | E3: Profit | F3: Margin % | G3: Units Sold | H3: Waste Units | I3: Waste % | J3: Growth % | K3: Lifecycle Status | L3: Test Record
A4: TEST-VAR001 | B4: Test Strawberry Jam 8 oz | C4: 150 | D4: 32.25 | E4: =tblProductScorecards[[#This Row],[Revenue]]-tblProductScorecards[[#This Row],[COGS]] | F4: =IFERROR(tblProductScorecards[[#This Row],[Profit]]/tblProductScorecards[[#This Row],[Revenue]],0) | G4: 15 | H4: 3 | I4: =IFERROR(tblProductScorecards[[#This Row],[Waste Units]]/(tblProductScorecards[[#This Row],[Units Sold]]+tblProductScorecards[[#This Row],[Waste Units]]),0) | J4: 0.1 | K4: =IF(tblProductScorecards[[#This Row],[Growth %]]>=0.2,"Growing",IF(tblProductScorecards[[#This Row],[Growth %]]<=-0.2,"Declining",IF(tblProductScorecards[[#This Row],[Units Sold]]<10,"New","Stable"))) | L4: Yes

Sheet Market_Opportunity
A1: MARKET OPPORTUNITY
A3: Market | B3: Revenue Growth Score | C3: Profit Growth Score | D3: Visit Frequency Score | E3: Reliability Score | F3: Opportunity Score | G3: Opportunity Band | H3: Recommended Action | I3: Test Record
A4: TEST-ORLANDO | B4: 80 | C4: 75 | D4: 60 | E4: 90 | F4: =tblMarketOpportunity[[#This Row],[Revenue Growth Score]]*0.30+tblMarketOpportunity[[#This Row],[Profit Growth Score]]*0.35+tblMarketOpportunity[[#This Row],[Visit Frequency Score]]*0.15+tblMarketOpportunity[[#This Row],[Reliability Score]]*0.20 | G4: =IF(tblMarketOpportunity[[#This Row],[Opportunity Score]]>=80,"High",IF(tblMarketOpportunity[[#This Row],[Opportunity Score]]>=60,"Medium","Low")) | H4: =IF(tblMarketOpportunity[[#This Row],[Opportunity Band]]="High","Increase Attendance",IF(tblMarketOpportunity[[#This Row],[Opportunity Band]]="Medium","Monitor","Review")) | I4: Yes

Sheet Release_Certification
A1: RELEASE CERTIFICATION
A3: Control | B3: Required Result | C3: Actual Result | D3: Pass/Fail | E3: Blocking | F3: Notes
A4: All Tests | B4: PASS | C4: PASS | D4: =IF(tblReleaseCertification[[#This Row],[Actual Result]]=tblReleaseCertification[[#This Row],[Required Result]],"PASS","FAIL") | E4: Yes | F4: Regression suite
A5: Import Errors | B5: 0 | C5: 0 | D5: =IF(tblReleaseCertification[[#This Row],[Actual Result]]=tblReleaseCertification[[#This Row],[Required Result]],"PASS","FAIL") | E5: Yes | F5: Open import errors
A6: Inventory Errors | B6: 0 | C6: 0 | D6: =IF(tblReleaseCertification[[#This Row],[Actual Result]]=tblReleaseCertification[[#This Row],[Required Result]],"PASS","FAIL") | E6: Yes | F6: Inventory movement errors
A7: Missing Costs | B7: 0 | C7: 0 | D7: =IF(tblReleaseCertification[[#This Row],[Actual Result]]=tblReleaseCertification[[#This Row],[Required Result]],"PASS","FAIL") | E7: Yes | F7: Product cost completeness
A8: Missing Recipes | B8: 0 | C8: 0 | D8: =IF(tblReleaseCertification[[#This Row],[Actual Result]]=tblReleaseCertification[[#This Row],[Required Result]],"PASS","FAIL") | E8: Yes | F8: Recipe completeness
A9: Health Score | B9: 95 | C9: 100 | D9: =IF(tblReleaseCertification[[#This Row],[Actual Result]]=tblReleaseCertification[[#This Row],[Required Result]],"PASS","FAIL") | E9: Yes | F9: Minimum quality score
A12: Release Decision | B12: =IF(COUNTIFS(tblReleaseCertification[Pass/Fail],"FAIL",tblReleaseCertification[Blocking],"Yes")=0,"RELEASE APPROVED","RELEASE BLOCKED")

Sheet Query_Architecture
A1: POWER QUERY ARCHITECTURE
A3: Query Name | B3: Layer | C3: Source | D3: Output | E3: Load Enabled | F3: Status | G3: Implementation Notes | H3: Test Record
A4: qrySquareSales_Landing | B4: Landing | C4: Square sales CSV folder | D4: Connection Only | E4: No | F4: STUB | G4: Connect real export folder | H4: No
A5: qrySquareCatalog_Landing | B5: Landing | C5: Square catalog export | D5: Connection Only | E5: No | F5: STUB | G5: Connect real catalog export | H5: No
A6: qrySales_Staging | B6: Staging | C6: qrySquareSales_Landing | D6: Connection Only | E6: No | F6: STUB | G6: Normalize types and deduplicate | H6: No
A7: qryCatalog_Staging | B7: Staging | C7: qrySquareCatalog_Landing | D7: Connection Only | E7: No | F7: STUB | G7: Normalize variation identifiers | H7: No
A8: qryProductMaster | B8: Business | C8: Catalog + Product Setup + Costs + Recipes | D8: tblProductMaster | E8: Yes | F8: STUB | G8: Left join on Variation ID | H8: No
A9: qryMarketSalesAssignment | B9: Business | C9: Sales + Weekly Markets | D9: Assigned Sales | E9: Yes | F9: STUB | G9: Use timestamps when source is connected | H9: No
A10: qryOpsKPIs | B10: Dashboard | C10: Curated business tables | D10: Operations Dashboard | E10: Yes | F10: STUB | G10: Dashboard aggregation | H10: No
A11: qryBusinessKPIs | B11: Dashboard | C11: Curated business tables | D11: Executive Dashboard | E11: Yes | F11: STUB | G11: Dashboard aggregation | H11: No

Sheet Reorder_Engine
A1: REORDER POINT ENGINE
A3: Ingredient | B3: On Hand | C3: Average Daily Usage | D3: Lead Time Days | E3: Safety Stock | F3: Reorder Point | G3: Needs Reorder | H3: Suggested Purchase Qty | I3: Estimated Unit Cost | J3: Estimated Purchase Cost | K3: Test Record
A4: Sugar | B4: 10 | C4: 1.5 | D4: 7 | E4: 5 | F4: =ROUNDUP(tblReorderEngine[[#This Row],[Average Daily Usage]]*tblReorderEngine[[#This Row],[Lead Time Days]]+tblReorderEngine[[#This Row],[Safety Stock]],0) | G4: =IF(tblReorderEngine[[#This Row],[On Hand]]<=tblReorderEngine[[#This Row],[Reorder Point]],"ORDER","OK") | H4: =MAX(0,tblReorderEngine[[#This Row],[Reorder Point]]-tblReorderEngine[[#This Row],[On Hand]]) | I4: 0.82 | J4: =tblReorderEngine[[#This Row],[Suggested Purchase Qty]]*tblReorderEngine[[#This Row],[Estimated Unit Cost]] | K4: Yes

Sheet Inventory_Valuation
A1: INVENTORY VALUATION
A3: Inventory Date | B3: Variation ID | C3: Product Name | D3: Ending Inventory | E3: Effective Product Cost | F3: Inventory Value | G3: Test Record
A4: 46027 | B4: TEST-VAR002 | C4: Test Strawberry Jam 16 oz | D4: 3 | E4: 3.8 | F4: =tblInventoryValuation[[#This Row],[Ending Inventory]]*tblInventoryValuation[[#This Row],[Effective Product Cost]] | G4: Yes

Sheet Dashboard_Testing
A1: Dashboard Testing Matrix
A3: Test ID | B3: Dashboard | C3: Control | D3: Expected | E3: Actual | F3: Status
A4: DT001 | B4: Executive | C4: Weekly Revenue | D4: Formula Exists | E4: MANUAL VERIFY | F4: PENDING
A5: DT002 | B5: Executive | C5: Weekly Profit | D5: Formula Exists | E5: MANUAL VERIFY | F5: PENDING
A6: DT003 | B6: Executive | C6: Monthly Revenue | D6: Formula Exists | E6: MANUAL VERIFY | F6: PENDING
A7: DT004 | B7: Data Quality | C7: Health Score | D7: 0-100 | E7: MANUAL VERIFY | F7: PENDING
A8: DT005 | B8: Release Cert | C8: Release Decision | D8: Exists | E8: MANUAL VERIFY | F8: PENDING

Sheet Test_Data
A1: Production Test Dataset
A3: Scenario | B3: Value
A4: Markets | B4: 2
A5: Products | B5: 4
A6: Weeks | B6: 8
A7: Vacation Week | B7: 1
A8: Missing Import | B8: 1
A9: Setup Required Products | B9: 2

Sheet Release_Readiness
A1: Release Readiness
A3: Regression Tests | B3: =Regression_Summary!B8
A4: Dashboard Tests | B4: =IF(COUNTIFS(tblRegressionTests[Category],"Dashboard",tblRegressionTests[Status],"FAIL")=0,"PASS","FAIL")
A5: Inventory Tests | B5: =IF(COUNTIFS(tblRegressionTests[Category],"Inventory",tblRegressionTests[Status],"FAIL")=0,"PASS","FAIL")
A6: Product Tests | B6: =IF(COUNTIFS(tblRegressionTests[Category],"Product",tblRegressionTests[Status],"FAIL")=0,"PASS","FAIL")
A7: Market/Governance Tests | B7: =IF(COUNTIFS(tblRegressionTests[Status],"FAIL",tblRegressionTests[Category],"Market")+COUNTIFS(tblRegressionTests[Status],"FAIL",tblRegressionTests[Category],"Governance")=0,"PASS","FAIL")
A10: Overall Status | B10: =IF(COUNTIF(B3:B7,"FAIL")>0,"BLOCKED","READY FOR PRODUCTION")

Sheet Regression_Tests
A1: 110-Test Automated Regression Suite
A3: Test ID | B3: Category | C3: Test Name | D3: Expected Result | E3: Actual Result | F3: Status | G3: Severity | H3: Notes
A4: RT001 | B4: Dashboard | C4: Executive weekly revenue formula | D4: PASS | E4: =IF(ISFORMULA(Executive_Dashboard!B4),"PASS","FAIL") | F4: =IF(OR(E4="NOT FOUND",E4="ERROR"),"FAIL",IF(AND(ISNUMBER(D4),ISNUMBER(E4)),IF(ABS(D4-E4)<0.01,"PASS","FAIL"),IF(D4=E4,"PASS","FAIL"))) | G4: Critical
A5: RT002 | B5: Dashboard | C5: Executive weekly profit formula | D5: PASS | E5: =IF(ISFORMULA(Executive_Dashboard!B5),"PASS","FAIL") | F5: =IF(OR(E5="NOT FOUND",E5="ERROR"),"FAIL",IF(AND(ISNUMBER(D5),ISNUMBER(E5)),IF(ABS(D5-E5)<0.01,"PASS","FAIL"),IF(D5=E5,"PASS","FAIL"))) | G5: Critical
A6: RT003 | B6: Dashboard | C6: Executive monthly revenue formula | D6: PASS | E6: =IF(ISFORMULA(Executive_Dashboard!E4),"PASS","FAIL") | F6: =IF(OR(E6="NOT FOUND",E6="ERROR"),"FAIL",IF(AND(ISNUMBER(D6),ISNUMBER(E6)),IF(ABS(D6-E6)<0.01,"PASS","FAIL"),IF(D6=E6,"PASS","FAIL"))) | G6: Critical
A7: RT004 | B7: Dashboard | C7: Executive monthly profit formula | D7: PASS | E7: =IF(ISFORMULA(Executive_Dashboard!E10),"PASS","FAIL") | F7: =IF(OR(E7="NOT FOUND",E7="ERROR"),"FAIL",IF(AND(ISNUMBER(D7),ISNUMBER(E7)),IF(ABS(D7-E7)<0.01,"PASS","FAIL"),IF(D7=E7,"PASS","FAIL"))) | G7: Critical
A8: RT005 | B8: Dashboard | C8: Executive YTD revenue formula | D8: PASS | E8: =IF(ISFORMULA(Executive_Dashboard!H4),"PASS","FAIL") | F8: =IF(OR(E8="NOT FOUND",E8="ERROR"),"FAIL",IF(AND(ISNUMBER(D8),ISNUMBER(E8)),IF(ABS(D8-E8)<0.01,"PASS","FAIL"),IF(D8=E8,"PASS","FAIL"))) | G8: Critical
A9: RT006 | B9: Dashboard | C9: Executive YTD profit formula | D9: PASS | E9: =IF(ISFORMULA(Executive_Dashboard!H10),"PASS","FAIL") | F9: =IF(OR(E9="NOT FOUND",E9="ERROR"),"FAIL",IF(AND(ISNUMBER(D9),ISNUMBER(E9)),IF(ABS(D9-E9)<0.01,"PASS","FAIL"),IF(D9=E9,"PASS","FAIL"))) | G9: Critical
A10: RT007 | B10: Dashboard | C10: Operations workbook health formula | D10: PASS | E10: =IF(ISFORMULA(Operations_Dashboard!B4),"PASS","FAIL") | F10: =IF(OR(E10="NOT FOUND",E10="ERROR"),"FAIL",IF(AND(ISNUMBER(D10),ISNUMBER(E10)),IF(ABS(D10-E10)<0.01,"PASS","FAIL"),IF(D10=E10,"PASS","FAIL"))) | G10: Critical
A11: RT008 | B11: Dashboard | C11: Operations missing import formula | D11: PASS | E11: =IF(ISFORMULA(Operations_Dashboard!B5),"PASS","FAIL") | F11: =IF(OR(E11="NOT FOUND",E11="ERROR"),"FAIL",IF(AND(ISNUMBER(D11),ISNUMBER(E11)),IF(ABS(D11-E11)<0.01,"PASS","FAIL"),IF(D11=E11,"PASS","FAIL"))) | G11: Critical
A12: RT009 | B12: Dashboard | C12: Operations product readiness formula | D12: PASS | E12: =IF(ISFORMULA(Operations_Dashboard!E4),"PASS","FAIL") | F12: =IF(OR(E12="NOT FOUND",E12="ERROR"),"FAIL",IF(AND(ISNUMBER(D12),ISNUMBER(E12)),IF(ABS(D12-E12)<0.01,"PASS","FAIL"),IF(D12=E12,"PASS","FAIL"))) | G12: Critical
A13: RT010 | B13: Dashboard | C13: Operations inventory snapshot formula | D13: PASS | E13: =IF(ISFORMULA(Operations_Dashboard!H4),"PASS","FAIL") | F13: =IF(OR(E13="NOT FOUND",E13="ERROR"),"FAIL",IF(AND(ISNUMBER(D13),ISNUMBER(E13)),IF(ABS(D13-E13)<0.01,"PASS","FAIL"),IF(D13=E13,"PASS","FAIL"))) | G13: Critical
A14: RT011 | B14: Dashboard | C14: Business weekly revenue formula | D14: PASS | E14: =IF(ISFORMULA(Business_Dashboard!B4),"PASS","FAIL") | F14: =IF(OR(E14="NOT FOUND",E14="ERROR"),"FAIL",IF(AND(ISNUMBER(D14),ISNUMBER(E14)),IF(ABS(D14-E14)<0.01,"PASS","FAIL"),IF(D14=E14,"PASS","FAIL"))) | G14: Critical
A15: RT012 | B15: Dashboard | C15: Business weekly profit formula | D15: PASS | E15: =IF(ISFORMULA(Business_Dashboard!B10),"PASS","FAIL") | F15: =IF(OR(E15="NOT FOUND",E15="ERROR"),"FAIL",IF(AND(ISNUMBER(D15),ISNUMBER(E15)),IF(ABS(D15-E15)<0.01,"PASS","FAIL"),IF(D15=E15,"PASS","FAIL"))) | G15: Critical
A16: RT013 | B16: Dashboard | C16: Best product formula | D16: PASS | E16: =IF(ISFORMULA(Business_Dashboard!E4),"PASS","FAIL") | F16: =IF(OR(E16="NOT FOUND",E16="ERROR"),"FAIL",IF(AND(ISNUMBER(D16),ISNUMBER(E16)),IF(ABS(D16-E16)<0.01,"PASS","FAIL"),IF(D16=E16,"PASS","FAIL"))) | G16: Critical
A17: RT014 | B17: Dashboard | C17: Best market formula | D17: PASS | E17: =IF(ISFORMULA(Business_Dashboard!E5),"PASS","FAIL") | F17: =IF(OR(E17="NOT FOUND",E17="ERROR"),"FAIL",IF(AND(ISNUMBER(D17),ISNUMBER(E17)),IF(ABS(D17-E17)<0.01,"PASS","FAIL"),IF(D17=E17,"PASS","FAIL"))) | G17: Critical
A18: RT015 | B18: Dashboard | C18: Setup completion formula | D18: PASS | E18: =IF(ISFORMULA(Business_Dashboard!H4),"PASS","FAIL") | F18: =IF(OR(E18="NOT FOUND",E18="ERROR"),"FAIL",IF(AND(ISNUMBER(D18),ISNUMBER(E18)),IF(ABS(D18-E18)<0.01,"PASS","FAIL"),IF(D18=E18,"PASS","FAIL"))) | G18: Critical
A19: RT016 | B19: Dashboard | C19: Waste percentage formula | D19: PASS | E19: =IF(ISFORMULA(Business_Dashboard!H5),"PASS","FAIL") | F19: =IF(OR(E19="NOT FOUND",E19="ERROR"),"FAIL",IF(AND(ISNUMBER(D19),ISNUMBER(E19)),IF(ABS(D19-E19)<0.01,"PASS","FAIL"),IF(D19=E19,"PASS","FAIL"))) | G19: Critical
A20: RT017 | B20: Dashboard | C20: Data quality health score formula | D20: PASS | E20: =IF(ISFORMULA(Data_Quality!B10),"PASS","FAIL") | F20: =IF(OR(E20="NOT FOUND",E20="ERROR"),"FAIL",IF(AND(ISNUMBER(D20),ISNUMBER(E20)),IF(ABS(D20-E20)<0.01,"PASS","FAIL"),IF(D20=E20,"PASS","FAIL"))) | G20: Critical
A21: RT018 | B21: Dashboard | C21: Data quality health status formula | D21: PASS | E21: =IF(ISFORMULA(Data_Quality!B11),"PASS","FAIL") | F21: =IF(OR(E21="NOT FOUND",E21="ERROR"),"FAIL",IF(AND(ISNUMBER(D21),ISNUMBER(E21)),IF(ABS(D21-E21)<0.01,"PASS","FAIL"),IF(D21=E21,"PASS","FAIL"))) | G21: Critical
A22: RT019 | B22: Dashboard | C22: Release decision formula | D22: PASS | E22: =IF(ISFORMULA(Release_Certification!B12),"PASS","FAIL") | F22: =IF(OR(E22="NOT FOUND",E22="ERROR"),"FAIL",IF(AND(ISNUMBER(D22),ISNUMBER(E22)),IF(ABS(D22-E22)<0.01,"PASS","FAIL"),IF(D22=E22,"PASS","FAIL"))) | G22: Critical
A23: RT020 | B23: Dashboard | C23: Forecast next week formula | D23: PASS | E23: =IF(ISFORMULA(Forecasting!F4),"PASS","FAIL") | F23: =IF(OR(E23="NOT FOUND",E23="ERROR"),"FAIL",IF(AND(ISNUMBER(D23),ISNUMBER(E23)),IF(ABS(D23-E23)<0.01,"PASS","FAIL"),IF(D23=E23,"PASS","FAIL"))) | G23: Critical
A24: RT021 | B24: Dashboard | C24: Forecast confidence formula | D24: PASS | E24: =IF(ISFORMULA(Forecasting!H4),"PASS","FAIL") | F24: =IF(OR(E24="NOT FOUND",E24="ERROR"),"FAIL",IF(AND(ISNUMBER(D24),ISNUMBER(E24)),IF(ABS(D24-E24)<0.01,"PASS","FAIL"),IF(D24=E24,"PASS","FAIL"))) | G24: Critical
A25: RT022 | B25: Dashboard | C25: Executive KPI excludes tests | D25: PASS | E25: =IF(ISNUMBER(SEARCH("Test Record",FORMULATEXT(Executive_Dashboard!B4))),"PASS","FAIL") | F25: =IF(OR(E25="NOT FOUND",E25="ERROR"),"FAIL",IF(AND(ISNUMBER(D25),ISNUMBER(E25)),IF(ABS(D25-E25)<0.01,"PASS","FAIL"),IF(D25=E25,"PASS","FAIL"))) | G25: Critical
A26: RT023 | B26: Dashboard | C26: Business KPI excludes tests | D26: PASS | E26: =IF(ISNUMBER(SEARCH("Test Record",FORMULATEXT(Business_Dashboard!B4))),"PASS","FAIL") | F26: =IF(OR(E26="NOT FOUND",E26="ERROR"),"FAIL",IF(AND(ISNUMBER(D26),ISNUMBER(E26)),IF(ABS(D26-E26)<0.01,"PASS","FAIL"),IF(D26=E26,"PASS","FAIL"))) | G26: Critical
A27: RT024 | B27: Dashboard | C27: Operations KPI excludes tests | D27: PASS | E27: =IF(ISNUMBER(SEARCH("Test Record",FORMULATEXT(Operations_Dashboard!B5))),"PASS","FAIL") | F27: =IF(OR(E27="NOT FOUND",E27="ERROR"),"FAIL",IF(AND(ISNUMBER(D27),ISNUMBER(E27)),IF(ABS(D27-E27)<0.01,"PASS","FAIL"),IF(D27=E27,"PASS","FAIL"))) | G27: Critical
A28: RT025 | B28: Dashboard | C28: Inventory dashboard has date | D28: PASS | E28: =IF(ISFORMULA(Business_Dashboard!H6),"PASS","FAIL") | F28: =IF(OR(E28="NOT FOUND",E28="ERROR"),"FAIL",IF(AND(ISNUMBER(D28),ISNUMBER(E28)),IF(ABS(D28-E28)<0.01,"PASS","FAIL"),IF(D28=E28,"PASS","FAIL"))) | G28: Critical
A29: RT026 | B29: Inventory | C29: Spoilage fixture available | D29: 20 | E29: =SUMIFS(tblInventory[Available],tblInventory[Test Key],"TEST-INV-SPOIL") | F29: =IF(OR(E29="NOT FOUND",E29="ERROR"),"FAIL",IF(AND(ISNUMBER(D29),ISNUMBER(E29)),IF(ABS(D29-E29)<0.01,"PASS","FAIL"),IF(D29=E29,"PASS","FAIL"))) | G29: Critical
A30: RT027 | B30: Inventory | C30: Spoilage fixture variance | D30: 3 | E30: =SUMIFS(tblInventory[Inventory Variance],tblInventory[Test Key],"TEST-INV-SPOIL") | F30: =IF(OR(E30="NOT FOUND",E30="ERROR"),"FAIL",IF(AND(ISNUMBER(D30),ISNUMBER(E30)),IF(ABS(D30-E30)<0.01,"PASS","FAIL"),IF(D30=E30,"PASS","FAIL"))) | G30: Critical
A31: RT028 | B31: Inventory | C31: Spoilage fixture spoilage | D31: 3 | E31: =SUMIFS(tblInventory[Spoilage],tblInventory[Test Key],"TEST-INV-SPOIL") | F31: =IF(OR(E31="NOT FOUND",E31="ERROR"),"FAIL",IF(AND(ISNUMBER(D31),ISNUMBER(E31)),IF(ABS(D31-E31)<0.01,"PASS","FAIL"),IF(D31=E31,"PASS","FAIL"))) | G31: Critical
A32: RT029 | B32: Inventory | C32: Spoilage fixture ending inventory | D32: 0 | E32: =SUMIFS(tblInventory[Ending Inventory],tblInventory[Test Key],"TEST-INV-SPOIL") | F32: =IF(OR(E32="NOT FOUND",E32="ERROR"),"FAIL",IF(AND(ISNUMBER(D32),ISNUMBER(E32)),IF(ABS(D32-E32)<0.01,"PASS","FAIL"),IF(D32=E32,"PASS","FAIL"))) | G32: Critical
A33: RT030 | B33: Inventory | C33: Carry fixture available | D33: 20 | E33: =SUMIFS(tblInventory[Available],tblInventory[Test Key],"TEST-INV-CARRY") | F33: =IF(OR(E33="NOT FOUND",E33="ERROR"),"FAIL",IF(AND(ISNUMBER(D33),ISNUMBER(E33)),IF(ABS(D33-E33)<0.01,"PASS","FAIL"),IF(D33=E33,"PASS","FAIL"))) | G33: Critical
A34: RT031 | B34: Inventory | C34: Carry fixture variance | D34: 3 | E34: =SUMIFS(tblInventory[Inventory Variance],tblInventory[Test Key],"TEST-INV-CARRY") | F34: =IF(OR(E34="NOT FOUND",E34="ERROR"),"FAIL",IF(AND(ISNUMBER(D34),ISNUMBER(E34)),IF(ABS(D34-E34)<0.01,"PASS","FAIL"),IF(D34=E34,"PASS","FAIL"))) | G34: Critical
A35: RT032 | B35: Inventory | C35: Carry fixture spoilage | D35: 0 | E35: =SUMIFS(tblInventory[Spoilage],tblInventory[Test Key],"TEST-INV-CARRY") | F35: =IF(OR(E35="NOT FOUND",E35="ERROR"),"FAIL",IF(AND(ISNUMBER(D35),ISNUMBER(E35)),IF(ABS(D35-E35)<0.01,"PASS","FAIL"),IF(D35=E35,"PASS","FAIL"))) | G35: Critical
A36: RT033 | B36: Inventory | C36: Carry fixture ending inventory | D36: 3 | E36: =SUMIFS(tblInventory[Ending Inventory],tblInventory[Test Key],"TEST-INV-CARRY") | F36: =IF(OR(E36="NOT FOUND",E36="ERROR"),"FAIL",IF(AND(ISNUMBER(D36),ISNUMBER(E36)),IF(ABS(D36-E36)<0.01,"PASS","FAIL"),IF(D36=E36,"PASS","FAIL"))) | G36: Critical
A37: RT034 | B37: Inventory | C37: Spoilage validation OK | D37: OK | E37: =INDEX(tblInventory[Validation],MATCH("TEST-INV-SPOIL",tblInventory[Test Key],0)) | F37: =IF(OR(E37="NOT FOUND",E37="ERROR"),"FAIL",IF(AND(ISNUMBER(D37),ISNUMBER(E37)),IF(ABS(D37-E37)<0.01,"PASS","FAIL"),IF(D37=E37,"PASS","FAIL"))) | G37: Critical
A38: RT035 | B38: Inventory | C38: Carry validation OK | D38: OK | E38: =INDEX(tblInventory[Validation],MATCH("TEST-INV-CARRY",tblInventory[Test Key],0)) | F38: =IF(OR(E38="NOT FOUND",E38="ERROR"),"FAIL",IF(AND(ISNUMBER(D38),ISNUMBER(E38)),IF(ABS(D38-E38)<0.01,"PASS","FAIL"),IF(D38=E38,"PASS","FAIL"))) | G38: Critical
A39: RT036 | B39: Inventory | C39: Available formula exists | D39: PASS | E39: =IF(ISFORMULA(Inventory!H4),"PASS","FAIL") | F39: =IF(OR(E39="NOT FOUND",E39="ERROR"),"FAIL",IF(AND(ISNUMBER(D39),ISNUMBER(E39)),IF(ABS(D39-E39)<0.01,"PASS","FAIL"),IF(D39=E39,"PASS","FAIL"))) | G39: Critical
A40: RT037 | B40: Inventory | C40: Variance formula exists | D40: PASS | E40: =IF(ISFORMULA(Inventory!I4),"PASS","FAIL") | F40: =IF(OR(E40="NOT FOUND",E40="ERROR"),"FAIL",IF(AND(ISNUMBER(D40),ISNUMBER(E40)),IF(ABS(D40-E40)<0.01,"PASS","FAIL"),IF(D40=E40,"PASS","FAIL"))) | G40: Critical
A41: RT038 | B41: Inventory | C41: Spoilage formula exists | D41: PASS | E41: =IF(ISFORMULA(Inventory!J4),"PASS","FAIL") | F41: =IF(OR(E41="NOT FOUND",E41="ERROR"),"FAIL",IF(AND(ISNUMBER(D41),ISNUMBER(E41)),IF(ABS(D41-E41)<0.01,"PASS","FAIL"),IF(D41=E41,"PASS","FAIL"))) | G41: Critical
A42: RT039 | B42: Inventory | C42: Ending formula exists | D42: PASS | E42: =IF(ISFORMULA(Inventory!K4),"PASS","FAIL") | F42: =IF(OR(E42="NOT FOUND",E42="ERROR"),"FAIL",IF(AND(ISNUMBER(D42),ISNUMBER(E42)),IF(ABS(D42-E42)<0.01,"PASS","FAIL"),IF(D42=E42,"PASS","FAIL"))) | G42: Critical
A43: RT040 | B43: Inventory | C43: Inventory validation formula exists | D43: PASS | E43: =IF(ISFORMULA(Inventory!L4),"PASS","FAIL") | F43: =IF(OR(E43="NOT FOUND",E43="ERROR"),"FAIL",IF(AND(ISNUMBER(D43),ISNUMBER(E43)),IF(ABS(D43-E43)<0.01,"PASS","FAIL"),IF(D43=E43,"PASS","FAIL"))) | G43: Critical
A44: RT041 | B44: Inventory | C44: Inventory test records excluded from dashboard | D44: 0 | E44: =COUNTIFS(tblInventory[Test Record],"Yes",tblInventory[Test Record],"No") | F44: =IF(OR(E44="NOT FOUND",E44="ERROR"),"FAIL",IF(AND(ISNUMBER(D44),ISNUMBER(E44)),IF(ABS(D44-E44)<0.01,"PASS","FAIL"),IF(D44=E44,"PASS","FAIL"))) | G44: Critical
A45: RT042 | B45: Inventory | C45: Inventory valuation formula exists | D45: PASS | E45: =IF(ISFORMULA(Inventory_Valuation!F4),"PASS","FAIL") | F45: =IF(OR(E45="NOT FOUND",E45="ERROR"),"FAIL",IF(AND(ISNUMBER(D45),ISNUMBER(E45)),IF(ABS(D45-E45)<0.01,"PASS","FAIL"),IF(D45=E45,"PASS","FAIL"))) | G45: Critical
A46: RT043 | B46: Inventory | C46: Inventory valuation fixture | D46: 11.4 | E46: =SUMIFS(tblInventoryValuation[Inventory Value],tblInventoryValuation[Variation ID],"TEST-VAR002") | F46: =IF(OR(E46="NOT FOUND",E46="ERROR"),"FAIL",IF(AND(ISNUMBER(D46),ISNUMBER(E46)),IF(ABS(D46-E46)<0.01,"PASS","FAIL"),IF(D46=E46,"PASS","FAIL"))) | G46: Critical
A47: RT044 | B47: Inventory | C47: Reorder point formula exists | D47: PASS | E47: =IF(ISFORMULA(Reorder_Engine!F4),"PASS","FAIL") | F47: =IF(OR(E47="NOT FOUND",E47="ERROR"),"FAIL",IF(AND(ISNUMBER(D47),ISNUMBER(E47)),IF(ABS(D47-E47)<0.01,"PASS","FAIL"),IF(D47=E47,"PASS","FAIL"))) | G47: Critical
A48: RT045 | B48: Inventory | C48: Reorder status formula exists | D48: PASS | E48: =IF(ISFORMULA(Reorder_Engine!G4),"PASS","FAIL") | F48: =IF(OR(E48="NOT FOUND",E48="ERROR"),"FAIL",IF(AND(ISNUMBER(D48),ISNUMBER(E48)),IF(ABS(D48-E48)<0.01,"PASS","FAIL"),IF(D48=E48,"PASS","FAIL"))) | G48: Critical
A49: RT046 | B49: Inventory | C49: Suggested purchase formula exists | D49: PASS | E49: =IF(ISFORMULA(Reorder_Engine!H4),"PASS","FAIL") | F49: =IF(OR(E49="NOT FOUND",E49="ERROR"),"FAIL",IF(AND(ISNUMBER(D49),ISNUMBER(E49)),IF(ABS(D49-E49)<0.01,"PASS","FAIL"),IF(D49=E49,"PASS","FAIL"))) | G49: Critical
A50: RT047 | B50: Inventory | C50: Suggested cost formula exists | D50: PASS | E50: =IF(ISFORMULA(Reorder_Engine!J4),"PASS","FAIL") | F50: =IF(OR(E50="NOT FOUND",E50="ERROR"),"FAIL",IF(AND(ISNUMBER(D50),ISNUMBER(E50)),IF(ABS(D50-E50)<0.01,"PASS","FAIL"),IF(D50=E50,"PASS","FAIL"))) | G50: Critical
A51: RT048 | B51: Inventory | C51: Reorder point fixture | D51: 16 | E51: =SUMIFS(tblReorderEngine[Reorder Point],tblReorderEngine[Ingredient],"Sugar") | F51: =IF(OR(E51="NOT FOUND",E51="ERROR"),"FAIL",IF(AND(ISNUMBER(D51),ISNUMBER(E51)),IF(ABS(D51-E51)<0.01,"PASS","FAIL"),IF(D51=E51,"PASS","FAIL"))) | G51: Critical
A52: RT049 | B52: Inventory | C52: Suggested purchase fixture | D52: 6 | E52: =SUMIFS(tblReorderEngine[Suggested Purchase Qty],tblReorderEngine[Ingredient],"Sugar") | F52: =IF(OR(E52="NOT FOUND",E52="ERROR"),"FAIL",IF(AND(ISNUMBER(D52),ISNUMBER(E52)),IF(ABS(D52-E52)<0.01,"PASS","FAIL"),IF(D52=E52,"PASS","FAIL"))) | G52: Critical
A53: RT050 | B53: Inventory | C53: Suggested purchase cost fixture | D53: 4.92 | E53: =SUMIFS(tblReorderEngine[Estimated Purchase Cost],tblReorderEngine[Ingredient],"Sugar") | F53: =IF(OR(E53="NOT FOUND",E53="ERROR"),"FAIL",IF(AND(ISNUMBER(D53),ISNUMBER(E53)),IF(ABS(D53-E53)<0.01,"PASS","FAIL"),IF(D53=E53,"PASS","FAIL"))) | G53: Critical
A54: RT051 | B54: Product | C54: Ready product status | D54: READY | E54: =INDEX(tblProductMaster[Product Status],MATCH("TEST-VAR001",tblProductMaster[Variation ID],0)) | F54: =IF(OR(E54="NOT FOUND",E54="ERROR"),"FAIL",IF(AND(ISNUMBER(D54),ISNUMBER(E54)),IF(ABS(D54-E54)<0.01,"PASS","FAIL"),IF(D54=E54,"PASS","FAIL"))) | G54: Critical
A55: RT052 | B55: Product | C55: Missing cost status | D55: SETUP REQUIRED | E55: =INDEX(tblProductMaster[Product Status],MATCH("TEST-VAR002",tblProductMaster[Variation ID],0)) | F55: =IF(OR(E55="NOT FOUND",E55="ERROR"),"FAIL",IF(AND(ISNUMBER(D55),ISNUMBER(E55)),IF(ABS(D55-E55)<0.01,"PASS","FAIL"),IF(D55=E55,"PASS","FAIL"))) | G55: Critical
A56: RT053 | B56: Product | C56: Missing recipe status | D56: SETUP REQUIRED | E56: =INDEX(tblProductMaster[Product Status],MATCH("TEST-VAR003",tblProductMaster[Variation ID],0)) | F56: =IF(OR(E56="NOT FOUND",E56="ERROR"),"FAIL",IF(AND(ISNUMBER(D56),ISNUMBER(E56)),IF(ABS(D56-E56)<0.01,"PASS","FAIL"),IF(D56=E56,"PASS","FAIL"))) | G56: Critical
A57: RT054 | B57: Product | C57: Configure product status | D57: CONFIGURE PRODUCT | E57: =INDEX(tblProductMaster[Product Status],MATCH("TEST-VAR004",tblProductMaster[Variation ID],0)) | F57: =IF(OR(E57="NOT FOUND",E57="ERROR"),"FAIL",IF(AND(ISNUMBER(D57),ISNUMBER(E57)),IF(ABS(D57-E57)<0.01,"PASS","FAIL"),IF(D57=E57,"PASS","FAIL"))) | G57: Critical
A58: RT055 | B58: Product | C58: Ready cost complete | D58: Yes | E58: =INDEX(tblProductMaster[Cost Complete],MATCH("TEST-VAR001",tblProductMaster[Variation ID],0)) | F58: =IF(OR(E58="NOT FOUND",E58="ERROR"),"FAIL",IF(AND(ISNUMBER(D58),ISNUMBER(E58)),IF(ABS(D58-E58)<0.01,"PASS","FAIL"),IF(D58=E58,"PASS","FAIL"))) | G58: Critical
A59: RT056 | B59: Product | C59: Missing cost detected | D59: No | E59: =INDEX(tblProductMaster[Cost Complete],MATCH("TEST-VAR002",tblProductMaster[Variation ID],0)) | F59: =IF(OR(E59="NOT FOUND",E59="ERROR"),"FAIL",IF(AND(ISNUMBER(D59),ISNUMBER(E59)),IF(ABS(D59-E59)<0.01,"PASS","FAIL"),IF(D59=E59,"PASS","FAIL"))) | G59: Critical
A60: RT057 | B60: Product | C60: Missing recipe detected | D60: No | E60: =INDEX(tblProductMaster[Recipe Complete],MATCH("TEST-VAR003",tblProductMaster[Variation ID],0)) | F60: =IF(OR(E60="NOT FOUND",E60="ERROR"),"FAIL",IF(AND(ISNUMBER(D60),ISNUMBER(E60)),IF(ABS(D60-E60)<0.01,"PASS","FAIL"),IF(D60=E60,"PASS","FAIL"))) | G60: Critical
A61: RT058 | B61: Product | C61: Shared recipe map exists | D61: 2 | E61: =COUNTIFS(tblProductRecipeMapping[Recipe ID],"TEST-R001") | F61: =IF(OR(E61="NOT FOUND",E61="ERROR"),"FAIL",IF(AND(ISNUMBER(D61),ISNUMBER(E61)),IF(ABS(D61-E61)<0.01,"PASS","FAIL"),IF(D61=E61,"PASS","FAIL"))) | G61: Critical
A62: RT059 | B62: Product | C62: Product cost record exists | D62: 1 | E62: =COUNTIFS(tblProductCosts[Variation ID],"TEST-VAR001") | F62: =IF(OR(E62="NOT FOUND",E62="ERROR"),"FAIL",IF(AND(ISNUMBER(D62),ISNUMBER(E62)),IF(ABS(D62-E62)<0.01,"PASS","FAIL"),IF(D62=E62,"PASS","FAIL"))) | G62: Critical
A63: RT060 | B63: Product | C63: Old cost review detected | D63: REVIEW COST | E63: =INDEX(tblProductCosts[Cost Review Status],MATCH("TEST-VAR003",tblProductCosts[Variation ID],0)) | F63: =IF(OR(E63="NOT FOUND",E63="ERROR"),"FAIL",IF(AND(ISNUMBER(D63),ISNUMBER(E63)),IF(ABS(D63-E63)<0.01,"PASS","FAIL"),IF(D63=E63,"PASS","FAIL"))) | G63: Critical
A64: RT061 | B64: Product | C64: Ingredient usage quantity | D64: 8 | E64: =SUMIFS(tblIngredientUsage[Quantity Used],tblIngredientUsage[Test Key],"TEST-USAGE-1") | F64: =IF(OR(E64="NOT FOUND",E64="ERROR"),"FAIL",IF(AND(ISNUMBER(D64),ISNUMBER(E64)),IF(ABS(D64-E64)<0.01,"PASS","FAIL"),IF(D64=E64,"PASS","FAIL"))) | G64: Critical
A65: RT062 | B65: Product | C65: Ingredient unit cost | D65: 2 | E65: =SUMIFS(tblIngredientUsage[Unit Cost],tblIngredientUsage[Test Key],"TEST-USAGE-1") | F65: =IF(OR(E65="NOT FOUND",E65="ERROR"),"FAIL",IF(AND(ISNUMBER(D65),ISNUMBER(E65)),IF(ABS(D65-E65)<0.01,"PASS","FAIL"),IF(D65=E65,"PASS","FAIL"))) | G65: Critical
A66: RT063 | B66: Product | C66: Ingredient usage cost | D66: 16 | E66: =SUMIFS(tblIngredientUsage[Usage Cost],tblIngredientUsage[Test Key],"TEST-USAGE-1") | F66: =IF(OR(E66="NOT FOUND",E66="ERROR"),"FAIL",IF(AND(ISNUMBER(D66),ISNUMBER(E66)),IF(ABS(D66-E66)<0.01,"PASS","FAIL"),IF(D66=E66,"PASS","FAIL"))) | G66: Critical
A67: RT064 | B67: Product | C67: Sales COGS fixture | D67: 32.25 | E67: =SUMIFS(tblSalesData[COGS],tblSalesData[Variation ID],"TEST-VAR001") | F67: =IF(OR(E67="NOT FOUND",E67="ERROR"),"FAIL",IF(AND(ISNUMBER(D67),ISNUMBER(E67)),IF(ABS(D67-E67)<0.01,"PASS","FAIL"),IF(D67=E67,"PASS","FAIL"))) | G67: Critical
A68: RT065 | B68: Product | C68: Scorecard profit formula | D68: PASS | E68: =IF(ISFORMULA(Product_Scorecards!E4),"PASS","FAIL") | F68: =IF(OR(E68="NOT FOUND",E68="ERROR"),"FAIL",IF(AND(ISNUMBER(D68),ISNUMBER(E68)),IF(ABS(D68-E68)<0.01,"PASS","FAIL"),IF(D68=E68,"PASS","FAIL"))) | G68: Critical
A69: RT066 | B69: Product | C69: Scorecard margin formula | D69: PASS | E69: =IF(ISFORMULA(Product_Scorecards!F4),"PASS","FAIL") | F69: =IF(OR(E69="NOT FOUND",E69="ERROR"),"FAIL",IF(AND(ISNUMBER(D69),ISNUMBER(E69)),IF(ABS(D69-E69)<0.01,"PASS","FAIL"),IF(D69=E69,"PASS","FAIL"))) | G69: Critical
A70: RT067 | B70: Product | C70: Scorecard waste formula | D70: PASS | E70: =IF(ISFORMULA(Product_Scorecards!I4),"PASS","FAIL") | F70: =IF(OR(E70="NOT FOUND",E70="ERROR"),"FAIL",IF(AND(ISNUMBER(D70),ISNUMBER(E70)),IF(ABS(D70-E70)<0.01,"PASS","FAIL"),IF(D70=E70,"PASS","FAIL"))) | G70: Critical
A71: RT068 | B71: Product | C71: Scorecard lifecycle formula | D71: PASS | E71: =IF(ISFORMULA(Product_Scorecards!K4),"PASS","FAIL") | F71: =IF(OR(E71="NOT FOUND",E71="ERROR"),"FAIL",IF(AND(ISNUMBER(D71),ISNUMBER(E71)),IF(ABS(D71-E71)<0.01,"PASS","FAIL"),IF(D71=E71,"PASS","FAIL"))) | G71: Critical
A72: RT069 | B72: Product | C72: Scorecard profit fixture | D72: 117.75 | E72: =SUMIFS(tblProductScorecards[Profit],tblProductScorecards[Variation ID],"TEST-VAR001") | F72: =IF(OR(E72="NOT FOUND",E72="ERROR"),"FAIL",IF(AND(ISNUMBER(D72),ISNUMBER(E72)),IF(ABS(D72-E72)<0.01,"PASS","FAIL"),IF(D72=E72,"PASS","FAIL"))) | G72: Critical
A73: RT070 | B73: Product | C73: Duplicate variation setup check | D73: 1 | E73: =COUNTIFS(tblProductSetup[Variation ID],"TEST-VAR001") | F73: =IF(OR(E73="NOT FOUND",E73="ERROR"),"FAIL",IF(AND(ISNUMBER(D73),ISNUMBER(E73)),IF(ABS(D73-E73)<0.01,"PASS","FAIL"),IF(D73=E73,"PASS","FAIL"))) | G73: Critical
A74: RT071 | B74: Market | C74: Attended category | D74: Attended | E74: =INDEX(tblWeeklyMarkets[Attendance Category],MATCH("TEST-MKT-01",tblWeeklyMarkets[Test Key],0)) | F74: =IF(OR(E74="NOT FOUND",E74="ERROR"),"FAIL",IF(AND(ISNUMBER(D74),ISNUMBER(E74)),IF(ABS(D74-E74)<0.01,"PASS","FAIL"),IF(D74=E74,"PASS","FAIL"))) | G74: Critical
A75: RT072 | B75: Market | C75: Vacation category | D75: Excluded | E75: =INDEX(tblWeeklyMarkets[Attendance Category],MATCH("TEST-MKT-02",tblWeeklyMarkets[Test Key],0)) | F75: =IF(OR(E75="NOT FOUND",E75="ERROR"),"FAIL",IF(AND(ISNUMBER(D75),ISNUMBER(E75)),IF(ABS(D75-E75)<0.01,"PASS","FAIL"),IF(D75=E75,"PASS","FAIL"))) | G75: Critical
A76: RT073 | B76: Market | C76: Market match count | D76: 1 | E76: =SUMIFS(tblWeeklyMarkets[Market Match Count],tblWeeklyMarkets[Test Key],"TEST-MKT-01") | F76: =IF(OR(E76="NOT FOUND",E76="ERROR"),"FAIL",IF(AND(ISNUMBER(D76),ISNUMBER(E76)),IF(ABS(D76-E76)<0.01,"PASS","FAIL"),IF(D76=E76,"PASS","FAIL"))) | G76: Critical
A77: RT074 | B77: Market | C77: Market fee fixture | D77: 40 | E77: =SUMIFS(tblWeeklyMarkets[Market Fee],tblWeeklyMarkets[Test Key],"TEST-MKT-01") | F77: =IF(OR(E77="NOT FOUND",E77="ERROR"),"FAIL",IF(AND(ISNUMBER(D77),ISNUMBER(E77)),IF(ABS(D77-E77)<0.01,"PASS","FAIL"),IF(D77=E77,"PASS","FAIL"))) | G77: Critical
A78: RT075 | B78: Market | C78: Actual mileage fixture | D78: 84 | E78: =SUMIFS(tblWeeklyMarkets[Actual Miles],tblWeeklyMarkets[Test Key],"TEST-MKT-01") | F78: =IF(OR(E78="NOT FOUND",E78="ERROR"),"FAIL",IF(AND(ISNUMBER(D78),ISNUMBER(E78)),IF(ABS(D78-E78)<0.01,"PASS","FAIL"),IF(D78=E78,"PASS","FAIL"))) | G78: Critical
A79: RT076 | B79: Market | C79: Travel cost fixture | D79: 56.28 | E79: =SUMIFS(tblWeeklyMarkets[Travel Cost],tblWeeklyMarkets[Test Key],"TEST-MKT-01") | F79: =IF(OR(E79="NOT FOUND",E79="ERROR"),"FAIL",IF(AND(ISNUMBER(D79),ISNUMBER(E79)),IF(ABS(D79-E79)<0.01,"PASS","FAIL"),IF(D79=E79,"PASS","FAIL"))) | G79: Critical
A80: RT077 | B80: Market | C80: Imported sales rows fixture | D80: 1 | E80: =SUMIFS(tblWeeklyMarkets[Imported Sales Rows],tblWeeklyMarkets[Test Key],"TEST-MKT-01") | F80: =IF(OR(E80="NOT FOUND",E80="ERROR"),"FAIL",IF(AND(ISNUMBER(D80),ISNUMBER(E80)),IF(ABS(D80-E80)<0.01,"PASS","FAIL"),IF(D80=E80,"PASS","FAIL"))) | G80: Critical
A81: RT078 | B81: Market | C81: Import status fixture | D81: IMPORTED | E81: =INDEX(tblWeeklyMarkets[Import Status],MATCH("TEST-MKT-01",tblWeeklyMarkets[Test Key],0)) | F81: =IF(OR(E81="NOT FOUND",E81="ERROR"),"FAIL",IF(AND(ISNUMBER(D81),ISNUMBER(E81)),IF(ABS(D81-E81)<0.01,"PASS","FAIL"),IF(D81=E81,"PASS","FAIL"))) | G81: Critical
A82: RT079 | B82: Market | C82: Vacation import status | D82: EXCLUDED | E82: =INDEX(tblWeeklyMarkets[Import Status],MATCH("TEST-MKT-02",tblWeeklyMarkets[Test Key],0)) | F82: =IF(OR(E82="NOT FOUND",E82="ERROR"),"FAIL",IF(AND(ISNUMBER(D82),ISNUMBER(E82)),IF(ABS(D82-E82)<0.01,"PASS","FAIL"),IF(D82=E82,"PASS","FAIL"))) | G82: Critical
A83: RT080 | B83: Market | C83: Market fee validation | D83: OK | E83: =INDEX(tblMarketMaster[Fee Validation],MATCH("TEST-ORLANDO",tblMarketMaster[Market],0)) | F83: =IF(OR(E83="NOT FOUND",E83="ERROR"),"FAIL",IF(AND(ISNUMBER(D83),ISNUMBER(E83)),IF(ABS(D83-E83)<0.01,"PASS","FAIL"),IF(D83=E83,"PASS","FAIL"))) | G83: Critical
A84: RT081 | B84: Market | C84: Market overlap count | D84: 0 | E84: =SUMIFS(tblMarketMaster[Overlap Count],tblMarketMaster[Market],"TEST-ORLANDO") | F84: =IF(OR(E84="NOT FOUND",E84="ERROR"),"FAIL",IF(AND(ISNUMBER(D84),ISNUMBER(E84)),IF(ABS(D84-E84)<0.01,"PASS","FAIL"),IF(D84=E84,"PASS","FAIL"))) | G84: Critical
A85: RT082 | B85: Market | C85: Market invalid date range blank | E85: =INDEX(tblMarketMaster[Invalid Date Range],MATCH("TEST-ORLANDO",tblMarketMaster[Market],0)) | F85: =IF(OR(E85="NOT FOUND",E85="ERROR"),"FAIL",IF(AND(ISNUMBER(D85),ISNUMBER(E85)),IF(ABS(D85-E85)<0.01,"PASS","FAIL"),IF(D85=E85,"PASS","FAIL"))) | G85: Critical
A86: RT083 | B86: Market | C86: Opportunity formula exists | D86: PASS | E86: =IF(ISFORMULA(Market_Opportunity!F4),"PASS","FAIL") | F86: =IF(OR(E86="NOT FOUND",E86="ERROR"),"FAIL",IF(AND(ISNUMBER(D86),ISNUMBER(E86)),IF(ABS(D86-E86)<0.01,"PASS","FAIL"),IF(D86=E86,"PASS","FAIL"))) | G86: Critical
A87: RT084 | B87: Market | C87: Opportunity band formula exists | D87: PASS | E87: =IF(ISFORMULA(Market_Opportunity!G4),"PASS","FAIL") | F87: =IF(OR(E87="NOT FOUND",E87="ERROR"),"FAIL",IF(AND(ISNUMBER(D87),ISNUMBER(E87)),IF(ABS(D87-E87)<0.01,"PASS","FAIL"),IF(D87=E87,"PASS","FAIL"))) | G87: Critical
A88: RT085 | B88: Market | C88: Opportunity action formula exists | D88: PASS | E88: =IF(ISFORMULA(Market_Opportunity!H4),"PASS","FAIL") | F88: =IF(OR(E88="NOT FOUND",E88="ERROR"),"FAIL",IF(AND(ISNUMBER(D88),ISNUMBER(E88)),IF(ABS(D88-E88)<0.01,"PASS","FAIL"),IF(D88=E88,"PASS","FAIL"))) | G88: Critical
A89: RT086 | B89: Market | C89: Opportunity score fixture | D89: 78.25 | E89: =SUMIFS(tblMarketOpportunity[Opportunity Score],tblMarketOpportunity[Market],"TEST-ORLANDO") | F89: =IF(OR(E89="NOT FOUND",E89="ERROR"),"FAIL",IF(AND(ISNUMBER(D89),ISNUMBER(E89)),IF(ABS(D89-E89)<0.01,"PASS","FAIL"),IF(D89=E89,"PASS","FAIL"))) | G89: Critical
A90: RT087 | B90: Market | C90: Ranking eligibility formula exists | D90: PASS | E90: =IF(ISFORMULA(Market_Rankings!C4),"PASS","FAIL") | F90: =IF(OR(E90="NOT FOUND",E90="ERROR"),"FAIL",IF(AND(ISNUMBER(D90),ISNUMBER(E90)),IF(ABS(D90-E90)<0.01,"PASS","FAIL"),IF(D90=E90,"PASS","FAIL"))) | G90: Critical
A91: RT088 | B91: Market | C91: Ranking confidence formula exists | D91: PASS | E91: =IF(ISFORMULA(Market_Rankings!I4),"PASS","FAIL") | F91: =IF(OR(E91="NOT FOUND",E91="ERROR"),"FAIL",IF(AND(ISNUMBER(D91),ISNUMBER(E91)),IF(ABS(D91-E91)<0.01,"PASS","FAIL"),IF(D91=E91,"PASS","FAIL"))) | G91: Critical
A92: RT089 | B92: Market | C92: Minimum visit setting | D92: 5 | E92: =MarketRankingMinimumVisits | F92: =IF(OR(E92="NOT FOUND",E92="ERROR"),"FAIL",IF(AND(ISNUMBER(D92),ISNUMBER(E92)),IF(ABS(D92-E92)<0.01,"PASS","FAIL"),IF(D92=E92,"PASS","FAIL"))) | G92: Critical
A93: RT090 | B93: Market | C93: Mileage rate setting | D93: 0.67 | E93: =MileageRate | F93: =IF(OR(E93="NOT FOUND",E93="ERROR"),"FAIL",IF(AND(ISNUMBER(D93),ISNUMBER(E93)),IF(ABS(D93-E93)<0.01,"PASS","FAIL"),IF(D93=E93,"PASS","FAIL"))) | G93: Critical
A94: RT091 | B94: Governance | C94: Regression test count | D94: 110 | E94: =ROWS(tblRegressionTests[Test ID]) | F94: =IF(OR(E94="NOT FOUND",E94="ERROR"),"FAIL",IF(AND(ISNUMBER(D94),ISNUMBER(E94)),IF(ABS(D94-E94)<0.01,"PASS","FAIL"),IF(D94=E94,"PASS","FAIL"))) | G94: Critical
A95: RT092 | B95: Governance | C95: Data dictionary table populated | D95: PASS | E95: =IF(ROWS(tblDataDictionary[Table])>0,"PASS","FAIL") | F95: =IF(OR(E95="NOT FOUND",E95="ERROR"),"FAIL",IF(AND(ISNUMBER(D95),ISNUMBER(E95)),IF(ABS(D95-E95)<0.01,"PASS","FAIL"),IF(D95=E95,"PASS","FAIL"))) | G95: Critical
A96: RT093 | B96: Governance | C96: Settings table populated | D96: PASS | E96: =IF(ROWS(tblSettings[Setting])>=6,"PASS","FAIL") | F96: =IF(OR(E96="NOT FOUND",E96="ERROR"),"FAIL",IF(AND(ISNUMBER(D96),ISNUMBER(E96)),IF(ABS(D96-E96)<0.01,"PASS","FAIL"),IF(D96=E96,"PASS","FAIL"))) | G96: Critical
A97: RT094 | B97: Governance | C97: Version table populated | D97: PASS | E97: =IF(ROWS(tblWorkbookVersion[Version])>=1,"PASS","FAIL") | F97: =IF(OR(E97="NOT FOUND",E97="ERROR"),"FAIL",IF(AND(ISNUMBER(D97),ISNUMBER(E97)),IF(ABS(D97-E97)<0.01,"PASS","FAIL"),IF(D97=E97,"PASS","FAIL"))) | G97: Critical
A98: RT095 | B98: Governance | C98: Error log table populated | D98: PASS | E98: =IF(ROWS(tblErrorLog[Error Type])>=1,"PASS","FAIL") | F98: =IF(OR(E98="NOT FOUND",E98="ERROR"),"FAIL",IF(AND(ISNUMBER(D98),ISNUMBER(E98)),IF(ABS(D98-E98)<0.01,"PASS","FAIL"),IF(D98=E98,"PASS","FAIL"))) | G98: Critical
A99: RT096 | B99: Governance | C99: Import log table exists | D99: PASS | E99: =IF(ROWS(tblImportLog[Status])>=1,"PASS","FAIL") | F99: =IF(OR(E99="NOT FOUND",E99="ERROR"),"FAIL",IF(AND(ISNUMBER(D99),ISNUMBER(E99)),IF(ABS(D99-E99)<0.01,"PASS","FAIL"),IF(D99=E99,"PASS","FAIL"))) | G99: Critical
A100: RT097 | B100: Governance | C100: Query architecture has 8 rows | D100: 8 | E100: =ROWS(tblQueryArchitecture[Query Name]) | F100: =IF(OR(E100="NOT FOUND",E100="ERROR"),"FAIL",IF(AND(ISNUMBER(D100),ISNUMBER(E100)),IF(ABS(D100-E100)<0.01,"PASS","FAIL"),IF(D100=E100,"PASS","FAIL"))) | G100: Critical
A101: RT098 | B101: Governance | C101: Product master has variation IDs | D101: PASS | E101: =IF(COUNTBLANK(tblProductMaster[Variation ID])=0,"PASS","FAIL") | F101: =IF(OR(E101="NOT FOUND",E101="ERROR"),"FAIL",IF(AND(ISNUMBER(D101),ISNUMBER(E101)),IF(ABS(D101-E101)<0.01,"PASS","FAIL"),IF(D101=E101,"PASS","FAIL"))) | G101: Critical
...

Sheet Regression_Summary
A1: Regression Test Dashboard
D3: Category | E3: Tests | F3: Failed
A4: Total Tests | B4: =ROWS(tblRegressionTests[Test ID]) | D4: Dashboard | E4: =COUNTIF(tblRegressionTests[Category],D4) | F4: =COUNTIFS(tblRegressionTests[Category],D4,tblRegressionTests[Status],"FAIL")
A5: Passed | B5: =COUNTIF(tblRegressionTests[Status],"PASS") | D5: Inventory | E5: =COUNTIF(tblRegressionTests[Category],D5) | F5: =COUNTIFS(tblRegressionTests[Category],D5,tblRegressionTests[Status],"FAIL")
A6: Failed | B6: =COUNTIF(tblRegressionTests[Status],"FAIL") | D6: Product | E6: =COUNTIF(tblRegressionTests[Category],D6) | F6: =COUNTIFS(tblRegressionTests[Category],D6,tblRegressionTests[Status],"FAIL")
A7: Pass Rate | B7: =IFERROR(B5/B4,0) | D7: Market | E7: =COUNTIF(tblRegressionTests[Category],D7) | F7: =COUNTIFS(tblRegressionTests[Category],D7,tblRegressionTests[Status],"FAIL")
A8: Release Gate | B8: =IF(B6=0,"PASS","BLOCKED") | D8: Governance | E8: =COUNTIF(tblRegressionTests[Category],D8) | F8: =COUNTIFS(tblRegressionTests[Category],D8,tblRegressionTests[Status],"FAIL")
